{
  "surah": 86,
  "analysis_type": "noon_ka_qaida",
  "schema_version": "1.0",
  "review": {
    "verified": 17,
    "pending": 0,
    "incorrect": 0,
    "total": 17
  },
  "summary": {
    "total_noon_sakin": 10,
    "total_tanween": 12,
    "total_izhar": 0,
    "total_idgham": 12,
    "total_iqlab": 1,
    "total_ikhfa": 8
  },
  "updated_at": "2026-03-12T02:03:42.773592+00:00",
  "created_at": "2026-02-22T07:13:12.388009+00:00",
  "ayahs": [
    {
      "ayah": 1,
      "text": "وَالسَّمَآءِ وَالطَّارِقِ ۝١ۙ",
      "status": "verified",
      "reviewer_comments": "",
      "updated_at": "2026-03-12T02:02:08.490291+00:00",
      "summary": {
        "total_noon_sakin": 0,
        "total_tanween": 0,
        "total_izhar": 0,
        "total_idgham": 0,
        "total_iqlab": 0,
        "total_ikhfa": 0
      },
      "explanations": [],
      "noon_sakin_positions": [],
      "tanween_positions": [],
      "izhar_halqi": [],
      "idgham": [],
      "iqlab": [],
      "ikhfa": []
    },
    {
      "ayah": 2,
      "text": "وَمَا͏ٓ اَدْرٰىكَ مَا الطَّارِقُ ۝٢ۙ",
      "status": "verified",
      "reviewer_comments": "",
      "updated_at": "2026-03-12T02:02:11.122668+00:00",
      "summary": {
        "total_noon_sakin": 0,
        "total_tanween": 0,
        "total_izhar": 0,
        "total_idgham": 0,
        "total_iqlab": 0,
        "total_ikhfa": 0
      },
      "explanations": [],
      "noon_sakin_positions": [],
      "tanween_positions": [],
      "izhar_halqi": [],
      "idgham": [],
      "iqlab": [],
      "ikhfa": []
    },
    {
      "ayah": 3,
      "text": "النَّجْمُ الثَّاقِبُ ۝٣ۙ",
      "status": "verified",
      "reviewer_comments": "",
      "updated_at": "2026-03-12T02:02:14.595727+00:00",
      "summary": {
        "total_noon_sakin": 1,
        "total_tanween": 0,
        "total_izhar": 0,
        "total_idgham": 1,
        "total_iqlab": 0,
        "total_ikhfa": 0
      },
      "explanations": [
        {
          "position": 2,
          "ayah": 3,
          "word": "النَّجْمُ",
          "letter_position": "the 3rd letter (position 3 of 5)",
          "next_word": "النَّجْمُ",
          "next_letter": "ن",
          "rule": "idgham_with_ghunnah",
          "highlighting": {
            "primary_letter": {
              "start": 2,
              "end": 4,
              "letter": "ن",
              "full_char": "نَّ",
              "index_in_word": 2
            },
            "word": {
              "start": 0,
              "end": 8,
              "text": "النَّجْمُ",
              "segments": [
                {
                  "index": 0,
                  "letter": "ا",
                  "full_char": "ا",
                  "raw_char": "ا",
                  "text_start": 0,
                  "text_end": 0
                },
                {
                  "index": 1,
                  "letter": "ل",
                  "full_char": "ل",
                  "raw_char": "ل",
                  "text_start": 1,
                  "text_end": 1
                },
                {
                  "index": 2,
                  "letter": "ن",
                  "full_char": "نَّ",
                  "raw_char": "نَّ",
                  "text_start": 2,
                  "text_end": 4
                },
                {
                  "index": 3,
                  "letter": "ج",
                  "full_char": "جْ",
                  "raw_char": "جْ",
                  "text_start": 5,
                  "text_end": 6
                },
                {
                  "index": 4,
                  "letter": "م",
                  "full_char": "مُ",
                  "raw_char": "مُ",
                  "text_start": 7,
                  "text_end": 8
                }
              ]
            },
            "letter_index_in_word": 2,
            "total_letters_in_word": 5,
            "next_letter": {
              "start": 5,
              "end": 6,
              "letter": "ج",
              "full_char": "جْ",
              "index_in_word": 3
            },
            "next_word": null
          },
          "explanation": "In the word 'النَّجْمُ', at the 3rd letter (position 3 of 5), we find Noon Sakin. The next letter 'ن' (within the same word) belongs to the Yarmaloon letters (ي ر م ل و ن). This means we apply Idgham (إدغام), which is the rule of merging. Since the letter 'ن' is one of (ي و م ن), you must perform idgham with a nasal sound (ghunnah), also called Idgham with Ghunnah (إدغام بغنة).",
          "urdu_explanation": "لفظ 'النَّجْمُ' میں، تیسرا حرف ، نون ساکن ہے۔ اگلا حرف 'ن' (اسی لفظ میں) یرملون (ي ر م ل و ن) میں سے ہے۔ یہاں ادغام ہوگا۔ چونکہ 'ن' (ی و م ن) میں سے ہے، اس لیے یہاں ادغام بغنہ ہوگا۔یعنی نون کو غنہ کے ساتھ ادا کریں۔",
          "is_cross_ayah": false
        }
      ],
      "noon_sakin_positions": [
        2
      ],
      "tanween_positions": [],
      "izhar_halqi": [],
      "idgham": [
        [
          2,
          "ن",
          true
        ]
      ],
      "iqlab": [],
      "ikhfa": []
    },
    {
      "ayah": 4,
      "text": "اِنْ كُلُّ نَفْسٍ لَّمَّا عَلَيْهَا حَافِظٌ ۝٤ؕ",
      "status": "verified",
      "reviewer_comments": "",
      "updated_at": "2026-03-12T02:02:20.974772+00:00",
      "summary": {
        "total_noon_sakin": 1,
        "total_tanween": 2,
        "total_izhar": 0,
        "total_idgham": 1,
        "total_iqlab": 0,
        "total_ikhfa": 2
      },
      "explanations": [
        {
          "position": 2,
          "ayah": 4,
          "word": "اِنْ",
          "letter_position": "the last letter (position 2 of 2)",
          "next_word": "كُلُّ",
          "next_letter": "ك",
          "rule": "ikhfa",
          "highlighting": {
            "primary_letter": {
              "start": 2,
              "end": 3,
              "letter": "ن",
              "full_char": "نْ",
              "index_in_word": 1
            },
            "word": {
              "start": 0,
              "end": 3,
              "text": "اِنْ",
              "segments": [
                {
                  "index": 0,
                  "letter": "ا",
                  "full_char": "اِ",
                  "raw_char": "اِ",
                  "text_start": 0,
                  "text_end": 1
                },
                {
                  "index": 1,
                  "letter": "ن",
                  "full_char": "نْ",
                  "raw_char": "نْ",
                  "text_start": 2,
                  "text_end": 3
                }
              ]
            },
            "letter_index_in_word": 1,
            "total_letters_in_word": 2,
            "next_letter": {
              "start": 5,
              "end": 6,
              "letter": "ك",
              "full_char": "كُ",
              "index_in_word": 0
            },
            "next_word": {
              "start": 98,
              "end": 102,
              "text": "كُلُّ",
              "segments": [
                {
                  "index": 0,
                  "letter": "ك",
                  "full_char": "كُ",
                  "raw_char": "كُ",
                  "text_start": 98,
                  "text_end": 99
                },
                {
                  "index": 1,
                  "letter": "ل",
                  "full_char": "لُّ",
                  "raw_char": "لُّ",
                  "text_start": 100,
                  "text_end": 102
                }
              ]
            }
          },
          "explanation": "In the word 'اِنْ', at the last letter (position 2 of 2), we find Noon Sakin. The next letter 'ك' (from the word 'كُلُّ') is not from the throat letters, not from Yarmaloon, not Ba, and not Alif. Therefore, we apply Ikhfa (إخفاء), which means you must hide or conceal the Noon with a nasal sound (ghunnah). The sound is between clear pronunciation and complete merging - not fully pronounced, not fully merged.",
          "urdu_explanation": "لفظ 'اِنْ' میں، آخری حرف ، نون ساکن ہے۔ اگلا حرف 'ك' (لفظ 'كُلُّ' سے) نہ حلقی حروف میں سے ہے، نہ یرملون، نہ با، اور نہ الف۔ یہاں اخفاء ہوگا۔ نون کو غنہ کے ساتھ چھپا کر بولیں۔",
          "is_cross_ayah": false
        },
        {
          "position": 15,
          "ayah": 4,
          "word": "نَفْسٍ",
          "letter_position": "the last letter (position 3 of 3)",
          "next_word": "لَّمَّا",
          "next_letter": "ل",
          "rule": "idgham_without_ghunnah",
          "highlighting": {
            "primary_letter": {
              "start": 15,
              "end": 16,
              "letter": "س",
              "full_char": "سٍ",
              "index_in_word": 2
            },
            "word": {
              "start": 11,
              "end": 16,
              "text": "نَفْسٍ",
              "segments": [
                {
                  "index": 0,
                  "letter": "ن",
                  "full_char": "نَ",
                  "raw_char": "نَ",
                  "text_start": 11,
                  "text_end": 12
                },
                {
                  "index": 1,
                  "letter": "ف",
                  "full_char": "فْ",
                  "raw_char": "فْ",
                  "text_start": 13,
                  "text_end": 14
                },
                {
                  "index": 2,
                  "letter": "س",
                  "full_char": "سٍ",
                  "raw_char": "سٍ",
                  "text_start": 15,
                  "text_end": 16
                }
              ]
            },
            "letter_index_in_word": 2,
            "total_letters_in_word": 3,
            "next_letter": {
              "start": 18,
              "end": 20,
              "letter": "ل",
              "full_char": "لَّ",
              "index_in_word": 0
            },
            "next_word": {
              "start": 111,
              "end": 117,
              "text": "لَّمَّا",
              "segments": [
                {
                  "index": 0,
                  "letter": "ل",
                  "full_char": "لَّ",
                  "raw_char": "لَّ",
                  "text_start": 111,
                  "text_end": 113
                },
                {
                  "index": 1,
                  "letter": "م",
                  "full_char": "مَّ",
                  "raw_char": "مَّ",
                  "text_start": 114,
                  "text_end": 116
                },
                {
                  "index": 2,
                  "letter": "ا",
                  "full_char": "ا",
                  "raw_char": "ا",
                  "text_start": 117,
                  "text_end": 117
                }
              ]
            }
          },
          "explanation": "In the word 'نَفْسٍ', at the last letter (position 3 of 3), we find Noon Tanween. The next letter 'ل' (from the word 'لَّمَّا') belongs to the Yarmaloon letters (ي ر م ل و ن). This means we apply Idgham (إدغام), which is the rule of merging. Since the letter 'ل' is one of (ل ر), you must perform idgham without a nasal sound (no ghunnah), also called Idgham without Ghunnah (إدغام بلا غنة).",
          "urdu_explanation": "لفظ 'نَفْسٍ' میں، آخری حرف ، نون تنوین ہے۔ اگلا حرف 'ل' (لفظ 'لَّمَّا' سے) یرملون (ي ر م ل و ن) میں سے ہے۔ یہاں ادغام ہوگا۔ چونکہ 'ل' (ل ر) میں سے ہے، اس لیے یہاں ادغام بلا غنہ ہوگا۔یعنی نون کو بغیر غنہ کے ادا کریں۔",
          "is_cross_ayah": false
        },
        {
          "position": 41,
          "ayah": 4,
          "word": "حَافِظٌ",
          "letter_position": "the last letter (position 4 of 4)",
          "next_word": "فَلْيَنْظُرِ",
          "next_letter": "ف",
          "rule": "ikhfa",
          "highlighting": {
            "primary_letter": {
              "start": 41,
              "end": 42,
              "letter": "ظ",
              "full_char": "ظٌ",
              "index_in_word": 3
            },
            "word": {
              "start": 36,
              "end": 42,
              "text": "حَافِظٌ",
              "segments": [
                {
                  "index": 0,
                  "letter": "ح",
                  "full_char": "حَ",
                  "raw_char": "حَ",
                  "text_start": 36,
                  "text_end": 37
                },
                {
                  "index": 1,
                  "letter": "ا",
                  "full_char": "ا",
                  "raw_char": "ا",
                  "text_start": 38,
                  "text_end": 38
                },
                {
                  "index": 2,
                  "letter": "ف",
                  "full_char": "فِ",
                  "raw_char": "فِ",
                  "text_start": 39,
                  "text_end": 40
                },
                {
                  "index": 3,
                  "letter": "ظ",
                  "full_char": "ظٌ",
                  "raw_char": "ظٌ",
                  "text_start": 41,
                  "text_end": 42
                }
              ]
            },
            "letter_index_in_word": 3,
            "total_letters_in_word": 4,
            "next_letter": null,
            "next_word": null
          },
          "explanation": "In the word 'حَافِظٌ', at the last letter (position 4 of 4), we find Noon Tanween. The next letter 'ف' (from the word 'فَلْيَنْظُرِ') is not from the throat letters, not from Yarmaloon, not Ba, and not Alif. Therefore, we apply Ikhfa (إخفاء), which means you must hide or conceal the Noon with a nasal sound (ghunnah). The sound is between clear pronunciation and complete merging - not fully pronounced, not fully merged.",
          "urdu_explanation": "لفظ 'حَافِظٌ' میں، آخری حرف ، نون تنوین ہے۔ اگلا حرف 'ف' (لفظ 'فَلْيَنْظُرِ' سے) نہ حلقی حروف میں سے ہے، نہ یرملون، نہ با، اور نہ الف۔ یہاں اخفاء ہوگا۔ نون کو غنہ کے ساتھ چھپا کر بولیں۔",
          "is_cross_ayah": true,
          "next_letter_ayah": 5,
          "next_letter_offset": 0
        }
      ],
      "noon_sakin_positions": [
        2
      ],
      "tanween_positions": [
        15,
        41
      ],
      "izhar_halqi": [],
      "idgham": [
        [
          15,
          "ل",
          false
        ]
      ],
      "iqlab": [],
      "ikhfa": [
        [
          2,
          "ك"
        ],
        [
          41,
          "ف"
        ]
      ]
    },
    {
      "ayah": 5,
      "text": "فَلْيَنْظُرِ الْاِنْسَانُ مِمَّ خُلِقَ ۝٥ؕ",
      "status": "verified",
      "reviewer_comments": "",
      "updated_at": "2026-03-12T02:02:28.226626+00:00",
      "summary": {
        "total_noon_sakin": 2,
        "total_tanween": 0,
        "total_izhar": 0,
        "total_idgham": 0,
        "total_iqlab": 0,
        "total_ikhfa": 2
      },
      "explanations": [
        {
          "position": 6,
          "ayah": 5,
          "word": "فَلْيَنْظُرِ",
          "letter_position": "the 4th letter (position 4 of 6)",
          "next_word": "فَلْيَنْظُرِ",
          "next_letter": "ظ",
          "rule": "ikhfa",
          "highlighting": {
            "primary_letter": {
              "start": 6,
              "end": 7,
              "letter": "ن",
              "full_char": "نْ",
              "index_in_word": 3
            },
            "word": {
              "start": 0,
              "end": 11,
              "text": "فَلْيَنْظُرِ",
              "segments": [
                {
                  "index": 0,
                  "letter": "ف",
                  "full_char": "فَ",
                  "raw_char": "فَ",
                  "text_start": 0,
                  "text_end": 1
                },
                {
                  "index": 1,
                  "letter": "ل",
                  "full_char": "لْ",
                  "raw_char": "لْ",
                  "text_start": 2,
                  "text_end": 3
                },
                {
                  "index": 2,
                  "letter": "ي",
                  "full_char": "يَ",
                  "raw_char": "يَ",
                  "text_start": 4,
                  "text_end": 5
                },
                {
                  "index": 3,
                  "letter": "ن",
                  "full_char": "نْ",
                  "raw_char": "نْ",
                  "text_start": 6,
                  "text_end": 7
                },
                {
                  "index": 4,
                  "letter": "ظ",
                  "full_char": "ظُ",
                  "raw_char": "ظُ",
                  "text_start": 8,
                  "text_end": 9
                },
                {
                  "index": 5,
                  "letter": "ر",
                  "full_char": "رِ",
                  "raw_char": "رِ",
                  "text_start": 10,
                  "text_end": 11
                }
              ]
            },
            "letter_index_in_word": 3,
            "total_letters_in_word": 6,
            "next_letter": {
              "start": 8,
              "end": 9,
              "letter": "ظ",
              "full_char": "ظُ",
              "index_in_word": 4
            },
            "next_word": null
          },
          "explanation": "In the word 'فَلْيَنْظُرِ', at the 4th letter (position 4 of 6), we find Noon Sakin. The next letter 'ظ' (within the same word) is not from the throat letters, not from Yarmaloon, not Ba, and not Alif. Therefore, we apply Ikhfa (إخفاء), which means you must hide or conceal the Noon with a nasal sound (ghunnah). The sound is between clear pronunciation and complete merging - not fully pronounced, not fully merged.",
          "urdu_explanation": "لفظ 'فَلْيَنْظُرِ' میں، چوتھا حرف ، نون ساکن ہے۔ اگلا حرف 'ظ' (اسی لفظ میں) نہ حلقی حروف میں سے ہے، نہ یرملون، نہ با، اور نہ الف۔ یہاں اخفاء ہوگا۔ نون کو غنہ کے ساتھ چھپا کر بولیں۔",
          "is_cross_ayah": false
        },
        {
          "position": 18,
          "ayah": 5,
          "word": "الْاِنْسَانُ",
          "letter_position": "the 4th letter (position 4 of 7)",
          "next_word": "الْاِنْسَانُ",
          "next_letter": "س",
          "rule": "ikhfa",
          "highlighting": {
            "primary_letter": {
              "start": 18,
              "end": 19,
              "letter": "ن",
              "full_char": "نْ",
              "index_in_word": 3
            },
            "word": {
              "start": 13,
              "end": 24,
              "text": "الْاِنْسَانُ",
              "segments": [
                {
                  "index": 0,
                  "letter": "ا",
                  "full_char": "ا",
                  "raw_char": "ا",
                  "text_start": 13,
                  "text_end": 13
                },
                {
                  "index": 1,
                  "letter": "ل",
                  "full_char": "لْ",
                  "raw_char": "لْ",
                  "text_start": 14,
                  "text_end": 15
                },
                {
                  "index": 2,
                  "letter": "ا",
                  "full_char": "اِ",
                  "raw_char": "اِ",
                  "text_start": 16,
                  "text_end": 17
                },
                {
                  "index": 3,
                  "letter": "ن",
                  "full_char": "نْ",
                  "raw_char": "نْ",
                  "text_start": 18,
                  "text_end": 19
                },
                {
                  "index": 4,
                  "letter": "س",
                  "full_char": "سَ",
                  "raw_char": "سَ",
                  "text_start": 20,
                  "text_end": 21
                },
                {
                  "index": 5,
                  "letter": "ا",
                  "full_char": "ا",
                  "raw_char": "ا",
                  "text_start": 22,
                  "text_end": 22
                },
                {
                  "index": 6,
                  "letter": "ن",
                  "full_char": "نُ",
                  "raw_char": "نُ",
                  "text_start": 23,
                  "text_end": 24
                }
              ]
            },
            "letter_index_in_word": 3,
            "total_letters_in_word": 7,
            "next_letter": {
              "start": 20,
              "end": 21,
              "letter": "س",
              "full_char": "سَ",
              "index_in_word": 4
            },
            "next_word": null
          },
          "explanation": "In the word 'الْاِنْسَانُ', at the 4th letter (position 4 of 7), we find Noon Sakin. The next letter 'س' (within the same word) is not from the throat letters, not from Yarmaloon, not Ba, and not Alif. Therefore, we apply Ikhfa (إخفاء), which means you must hide or conceal the Noon with a nasal sound (ghunnah). The sound is between clear pronunciation and complete merging - not fully pronounced, not fully merged.",
          "urdu_explanation": "لفظ 'الْاِنْسَانُ' میں، چوتھا حرف ، نون ساکن ہے۔ اگلا حرف 'س' (اسی لفظ میں) نہ حلقی حروف میں سے ہے، نہ یرملون، نہ با، اور نہ الف۔ یہاں اخفاء ہوگا۔ نون کو غنہ کے ساتھ چھپا کر بولیں۔",
          "is_cross_ayah": false
        }
      ],
      "noon_sakin_positions": [
        6,
        18
      ],
      "tanween_positions": [],
      "izhar_halqi": [],
      "idgham": [],
      "iqlab": [],
      "ikhfa": [
        [
          6,
          "ظ"
        ],
        [
          18,
          "س"
        ]
      ]
    },
    {
      "ayah": 6,
      "text": "خُلِقَ مِنْ مَّآءٍ دَافِقٍ ۝٦ۙ",
      "status": "verified",
      "reviewer_comments": "",
      "updated_at": "2026-03-12T02:02:38.368757+00:00",
      "summary": {
        "total_noon_sakin": 1,
        "total_tanween": 2,
        "total_izhar": 0,
        "total_idgham": 2,
        "total_iqlab": 0,
        "total_ikhfa": 1
      },
      "explanations": [
        {
          "position": 9,
          "ayah": 6,
          "word": "مِنْ",
          "letter_position": "the last letter (position 2 of 2)",
          "next_word": "مَّآءٍ",
          "next_letter": "م",
          "rule": "idgham_with_ghunnah",
          "highlighting": {
            "primary_letter": {
              "start": 9,
              "end": 10,
              "letter": "ن",
              "full_char": "نْ",
              "index_in_word": 1
            },
            "word": {
              "start": 7,
              "end": 10,
              "text": "مِنْ",
              "segments": [
                {
                  "index": 0,
                  "letter": "م",
                  "full_char": "مِ",
                  "raw_char": "مِ",
                  "text_start": 7,
                  "text_end": 8
                },
                {
                  "index": 1,
                  "letter": "ن",
                  "full_char": "نْ",
                  "raw_char": "نْ",
                  "text_start": 9,
                  "text_end": 10
                }
              ]
            },
            "letter_index_in_word": 1,
            "total_letters_in_word": 2,
            "next_letter": {
              "start": 12,
              "end": 14,
              "letter": "م",
              "full_char": "مَّ",
              "index_in_word": 0
            },
            "next_word": {
              "start": 196,
              "end": 202,
              "text": "مَّآءٍ",
              "segments": [
                {
                  "index": 0,
                  "letter": "م",
                  "full_char": "مَّ",
                  "raw_char": "مَّ",
                  "text_start": 196,
                  "text_end": 198
                },
                {
                  "index": 1,
                  "letter": "ا",
                  "full_char": "ا",
                  "raw_char": "آ",
                  "text_start": 199,
                  "text_end": 200
                },
                {
                  "index": 2,
                  "letter": "ء",
                  "full_char": "ءٍ",
                  "raw_char": "ءٍ",
                  "text_start": 201,
                  "text_end": 202
                }
              ]
            }
          },
          "explanation": "In the word 'مِنْ', at the last letter (position 2 of 2), we find Noon Sakin. The next letter 'م' (from the word 'مَّآءٍ') belongs to the Yarmaloon letters (ي ر م ل و ن). This means we apply Idgham (إدغام), which is the rule of merging. Since the letter 'م' is one of (ي و م ن), you must perform idgham with a nasal sound (ghunnah), also called Idgham with Ghunnah (إدغام بغنة).",
          "urdu_explanation": "لفظ 'مِنْ' میں، آخری حرف ، نون ساکن ہے۔ اگلا حرف 'م' (لفظ 'مَّآءٍ' سے) یرملون (ي ر م ل و ن) میں سے ہے۔ یہاں ادغام ہوگا۔ چونکہ 'م' (ی و م ن) میں سے ہے، اس لیے یہاں ادغام بغنہ ہوگا۔یعنی نون کو غنہ کے ساتھ ادا کریں۔",
          "is_cross_ayah": false
        },
        {
          "position": 17,
          "ayah": 6,
          "word": "مَّآءٍ",
          "letter_position": "the last letter (position 3 of 3)",
          "next_word": "دَافِقٍ",
          "next_letter": "د",
          "rule": "ikhfa",
          "highlighting": {
            "primary_letter": {
              "start": 17,
              "end": 18,
              "letter": "ء",
              "full_char": "ءٍ",
              "index_in_word": 2
            },
            "word": {
              "start": 12,
              "end": 18,
              "text": "مَّآءٍ",
              "segments": [
                {
                  "index": 0,
                  "letter": "م",
                  "full_char": "مَّ",
                  "raw_char": "مَّ",
                  "text_start": 12,
                  "text_end": 14
                },
                {
                  "index": 1,
                  "letter": "ا",
                  "full_char": "ا",
                  "raw_char": "آ",
                  "text_start": 15,
                  "text_end": 16
                },
                {
                  "index": 2,
                  "letter": "ء",
                  "full_char": "ءٍ",
                  "raw_char": "ءٍ",
                  "text_start": 17,
                  "text_end": 18
                }
              ]
            },
            "letter_index_in_word": 2,
            "total_letters_in_word": 3,
            "next_letter": {
              "start": 20,
              "end": 21,
              "letter": "د",
              "full_char": "دَ",
              "index_in_word": 0
            },
            "next_word": {
              "start": 204,
              "end": 210,
              "text": "دَافِقٍ",
              "segments": [
                {
                  "index": 0,
                  "letter": "د",
                  "full_char": "دَ",
                  "raw_char": "دَ",
                  "text_start": 204,
                  "text_end": 205
                },
                {
                  "index": 1,
                  "letter": "ا",
                  "full_char": "ا",
                  "raw_char": "ا",
                  "text_start": 206,
                  "text_end": 206
                },
                {
                  "index": 2,
                  "letter": "ف",
                  "full_char": "فِ",
                  "raw_char": "فِ",
                  "text_start": 207,
                  "text_end": 208
                },
                {
                  "index": 3,
                  "letter": "ق",
                  "full_char": "قٍ",
                  "raw_char": "قٍ",
                  "text_start": 209,
                  "text_end": 210
                }
              ]
            }
          },
          "explanation": "In the word 'مَّآءٍ', at the last letter (position 3 of 3), we find Noon Tanween. The next letter 'د' (from the word 'دَافِقٍ') is not from the throat letters, not from Yarmaloon, not Ba, and not Alif. Therefore, we apply Ikhfa (إخفاء), which means you must hide or conceal the Noon with a nasal sound (ghunnah). The sound is between clear pronunciation and complete merging - not fully pronounced, not fully merged.",
          "urdu_explanation": "لفظ 'مَّآءٍ' میں، آخری حرف ، نون تنوین ہے۔ اگلا حرف 'د' (لفظ 'دَافِقٍ' سے) نہ حلقی حروف میں سے ہے، نہ یرملون، نہ با، اور نہ الف۔ یہاں اخفاء ہوگا۔ نون کو غنہ کے ساتھ چھپا کر بولیں۔",
          "is_cross_ayah": false
        },
        {
          "position": 25,
          "ayah": 6,
          "word": "دَافِقٍ",
          "letter_position": "the last letter (position 4 of 4)",
          "next_word": "يَّخْرُجُ",
          "next_letter": "ي",
          "rule": "idgham_with_ghunnah",
          "highlighting": {
            "primary_letter": {
              "start": 25,
              "end": 26,
              "letter": "ق",
              "full_char": "قٍ",
              "index_in_word": 3
            },
            "word": {
              "start": 20,
              "end": 26,
              "text": "دَافِقٍ",
              "segments": [
                {
                  "index": 0,
                  "letter": "د",
                  "full_char": "دَ",
                  "raw_char": "دَ",
                  "text_start": 20,
                  "text_end": 21
                },
                {
                  "index": 1,
                  "letter": "ا",
                  "full_char": "ا",
                  "raw_char": "ا",
                  "text_start": 22,
                  "text_end": 22
                },
                {
                  "index": 2,
                  "letter": "ف",
                  "full_char": "فِ",
                  "raw_char": "فِ",
                  "text_start": 23,
                  "text_end": 24
                },
                {
                  "index": 3,
                  "letter": "ق",
                  "full_char": "قٍ",
                  "raw_char": "قٍ",
                  "text_start": 25,
                  "text_end": 26
                }
              ]
            },
            "letter_index_in_word": 3,
            "total_letters_in_word": 4,
            "next_letter": null,
            "next_word": null
          },
          "explanation": "In the word 'دَافِقٍ', at the last letter (position 4 of 4), we find Noon Tanween. The next letter 'ي' (from the word 'يَّخْرُجُ') belongs to the Yarmaloon letters (ي ر م ل و ن). This means we apply Idgham (إدغام), which is the rule of merging. Since the letter 'ي' is one of (ي و م ن), you must perform idgham with a nasal sound (ghunnah), also called Idgham with Ghunnah (إدغام بغنة).",
          "urdu_explanation": "لفظ 'دَافِقٍ' میں، آخری حرف ، نون تنوین ہے۔ اگلا حرف 'ي' (لفظ 'يَّخْرُجُ' سے) یرملون (ي ر م ل و ن) میں سے ہے۔ یہاں ادغام ہوگا۔ چونکہ 'ي' (ی و م ن) میں سے ہے، اس لیے یہاں ادغام بغنہ ہوگا۔یعنی نون کو غنہ کے ساتھ ادا کریں۔",
          "is_cross_ayah": true,
          "next_letter_ayah": 7,
          "next_letter_offset": 0
        }
      ],
      "noon_sakin_positions": [
        9
      ],
      "tanween_positions": [
        17,
        25
      ],
      "izhar_halqi": [],
      "idgham": [
        [
          9,
          "م",
          true
        ],
        [
          25,
          "ي",
          true
        ]
      ],
      "iqlab": [],
      "ikhfa": [
        [
          17,
          "د"
        ]
      ]
    },
    {
      "ayah": 7,
      "text": "يَّخْرُجُ مِنْۢ بَيْنِ الصُّلْبِ وَالتَّرَآىِٕبِ ۝٧ؕ",
      "status": "verified",
      "reviewer_comments": "",
      "updated_at": "2026-03-12T02:02:42.085444+00:00",
      "summary": {
        "total_noon_sakin": 1,
        "total_tanween": 0,
        "total_izhar": 0,
        "total_idgham": 0,
        "total_iqlab": 1,
        "total_ikhfa": 0
      },
      "explanations": [
        {
          "position": 12,
          "ayah": 7,
          "word": "مِنْۢ",
          "letter_position": "the last letter (position 2 of 2)",
          "next_word": "بَيْنِ",
          "next_letter": "ب",
          "rule": "iqlab",
          "highlighting": {
            "primary_letter": {
              "start": 12,
              "end": 14,
              "letter": "ن",
              "full_char": "نْ",
              "index_in_word": 1
            },
            "word": {
              "start": 10,
              "end": 14,
              "text": "مِنْۢ",
              "segments": [
                {
                  "index": 0,
                  "letter": "م",
                  "full_char": "مِ",
                  "raw_char": "مِ",
                  "text_start": 10,
                  "text_end": 11
                },
                {
                  "index": 1,
                  "letter": "ن",
                  "full_char": "نْ",
                  "raw_char": "نْۢ",
                  "text_start": 12,
                  "text_end": 14
                }
              ]
            },
            "letter_index_in_word": 1,
            "total_letters_in_word": 2,
            "next_letter": {
              "start": 16,
              "end": 17,
              "letter": "ب",
              "full_char": "بَ",
              "index_in_word": 0
            },
            "next_word": {
              "start": 232,
              "end": 237,
              "text": "بَيْنِ",
              "segments": [
                {
                  "index": 0,
                  "letter": "ب",
                  "full_char": "بَ",
                  "raw_char": "بَ",
                  "text_start": 232,
                  "text_end": 233
                },
                {
                  "index": 1,
                  "letter": "ي",
                  "full_char": "يْ",
                  "raw_char": "يْ",
                  "text_start": 234,
                  "text_end": 235
                },
                {
                  "index": 2,
                  "letter": "ن",
                  "full_char": "نِ",
                  "raw_char": "نِ",
                  "text_start": 236,
                  "text_end": 237
                }
              ]
            }
          },
          "explanation": "In the word 'مِنْۢ', at the last letter (position 2 of 2), we find Noon Sakin. The next letter 'ب' (Ba) comes from the word 'بَيْنِ'. When this happens, we apply Iqlab (إقلاب), which means you must convert the sound of Noon into a Meem (م) sound, and hold it with a nasal sound (ghunnah) for two counts. Your lips should come together as if pronouncing Meem.",
          "urdu_explanation": "لفظ 'مِنْۢ' میں، آخری حرف ، نون ساکن ہے۔ اگلا حرف 'ب' (با) لفظ 'بَيْنِ' سے آتا ہے۔ یہاں اقلاب ہوگا۔ نون کی آواز کو میم (م) میں بدل دیں اور غنہ کے ساتھ بولیں۔ ہونٹ میم کی طرح ملیں۔",
          "is_cross_ayah": false
        }
      ],
      "noon_sakin_positions": [
        12
      ],
      "tanween_positions": [],
      "izhar_halqi": [],
      "idgham": [],
      "iqlab": [
        12
      ],
      "ikhfa": []
    },
    {
      "ayah": 8,
      "text": "اِنَّهٗ عَلٰي رَجْعِهٖ لَقَادِرٌ ۝٨ؕ",
      "status": "verified",
      "reviewer_comments": "",
      "updated_at": "2026-03-12T02:02:56.295153+00:00",
      "summary": {
        "total_noon_sakin": 1,
        "total_tanween": 1,
        "total_izhar": 0,
        "total_idgham": 2,
        "total_iqlab": 0,
        "total_ikhfa": 0
      },
      "explanations": [
        {
          "position": 2,
          "ayah": 8,
          "word": "اِنَّهٗ",
          "letter_position": "the 2nd letter (position 2 of 3)",
          "next_word": "اِنَّهٗ",
          "next_letter": "ن",
          "rule": "idgham_with_ghunnah",
          "highlighting": {
            "primary_letter": {
              "start": 2,
              "end": 4,
              "letter": "ن",
              "full_char": "نَّ",
              "index_in_word": 1
            },
            "word": {
              "start": 0,
              "end": 6,
              "text": "اِنَّهٗ",
              "segments": [
                {
                  "index": 0,
                  "letter": "ا",
                  "full_char": "اِ",
                  "raw_char": "اِ",
                  "text_start": 0,
                  "text_end": 1
                },
                {
                  "index": 1,
                  "letter": "ن",
                  "full_char": "نَّ",
                  "raw_char": "نَّ",
                  "text_start": 2,
                  "text_end": 4
                },
                {
                  "index": 2,
                  "letter": "ه",
                  "full_char": "هٗ",
                  "raw_char": "هٗ",
                  "text_start": 5,
                  "text_end": 6
                }
              ]
            },
            "letter_index_in_word": 1,
            "total_letters_in_word": 3,
            "next_letter": {
              "start": 5,
              "end": 6,
              "letter": "ه",
              "full_char": "هٗ",
              "index_in_word": 2
            },
            "next_word": null
          },
          "explanation": "In the word 'اِنَّهٗ', at the 2nd letter (position 2 of 3), we find Noon Sakin. The next letter 'ن' (within the same word) belongs to the Yarmaloon letters (ي ر م ل و ن). This means we apply Idgham (إدغام), which is the rule of merging. Since the letter 'ن' is one of (ي و م ن), you must perform idgham with a nasal sound (ghunnah), also called Idgham with Ghunnah (إدغام بغنة).",
          "urdu_explanation": "لفظ 'اِنَّهٗ' میں، دوسرا حرف ، نون ساکن ہے۔ اگلا حرف 'ن' (اسی لفظ میں) یرملون (ي ر م ل و ن) میں سے ہے۔ یہاں ادغام ہوگا۔ چونکہ 'ن' (ی و م ن) میں سے ہے، اس لیے یہاں ادغام بغنہ ہوگا۔یعنی نون کو غنہ کے ساتھ ادا کریں۔",
          "is_cross_ayah": false
        },
        {
          "position": 30,
          "ayah": 8,
          "word": "لَقَادِرٌ",
          "letter_position": "the last letter (position 5 of 5)",
          "next_word": "يَوْمَ",
          "next_letter": "ي",
          "rule": "idgham_with_ghunnah",
          "highlighting": {
            "primary_letter": {
              "start": 30,
              "end": 31,
              "letter": "ر",
              "full_char": "رٌ",
              "index_in_word": 4
            },
            "word": {
              "start": 23,
              "end": 31,
              "text": "لَقَادِرٌ",
              "segments": [
                {
                  "index": 0,
                  "letter": "ل",
                  "full_char": "لَ",
                  "raw_char": "لَ",
                  "text_start": 23,
                  "text_end": 24
                },
                {
                  "index": 1,
                  "letter": "ق",
                  "full_char": "قَ",
                  "raw_char": "قَ",
                  "text_start": 25,
                  "text_end": 26
                },
                {
                  "index": 2,
                  "letter": "ا",
                  "full_char": "ا",
                  "raw_char": "ا",
                  "text_start": 27,
                  "text_end": 27
                },
                {
                  "index": 3,
                  "letter": "د",
                  "full_char": "دِ",
                  "raw_char": "دِ",
                  "text_start": 28,
                  "text_end": 29
                },
                {
                  "index": 4,
                  "letter": "ر",
                  "full_char": "رٌ",
                  "raw_char": "رٌ",
                  "text_start": 30,
                  "text_end": 31
                }
              ]
            },
            "letter_index_in_word": 4,
            "total_letters_in_word": 5,
            "next_letter": null,
            "next_word": null
          },
          "explanation": "In the word 'لَقَادِرٌ', at the last letter (position 5 of 5), we find Noon Tanween. The next letter 'ي' (from the word 'يَوْمَ') belongs to the Yarmaloon letters (ي ر م ل و ن). This means we apply Idgham (إدغام), which is the rule of merging. Since the letter 'ي' is one of (ي و م ن), you must perform idgham with a nasal sound (ghunnah), also called Idgham with Ghunnah (إدغام بغنة).",
          "urdu_explanation": "لفظ 'لَقَادِرٌ' میں، آخری حرف ، نون تنوین ہے۔ اگلا حرف 'ي' (لفظ 'يَوْمَ' سے) یرملون (ي ر م ل و ن) میں سے ہے۔ یہاں ادغام ہوگا۔ چونکہ 'ي' (ی و م ن) میں سے ہے، اس لیے یہاں ادغام بغنہ ہوگا۔یعنی نون کو غنہ کے ساتھ ادا کریں۔",
          "is_cross_ayah": true,
          "next_letter_ayah": 9,
          "next_letter_offset": 0
        }
      ],
      "noon_sakin_positions": [
        2
      ],
      "tanween_positions": [
        30
      ],
      "izhar_halqi": [],
      "idgham": [
        [
          2,
          "ن",
          true
        ],
        [
          30,
          "ي",
          true
        ]
      ],
      "iqlab": [],
      "ikhfa": []
    },
    {
      "ayah": 9,
      "text": "يَوْمَ تُبْلَي السَّرَآىِٕرُ ۝٩ۙ",
      "status": "verified",
      "reviewer_comments": "",
      "updated_at": "2026-03-12T02:02:58.070009+00:00",
      "summary": {
        "total_noon_sakin": 0,
        "total_tanween": 0,
        "total_izhar": 0,
        "total_idgham": 0,
        "total_iqlab": 0,
        "total_ikhfa": 0
      },
      "explanations": [],
      "noon_sakin_positions": [],
      "tanween_positions": [],
      "izhar_halqi": [],
      "idgham": [],
      "iqlab": [],
      "ikhfa": []
    },
    {
      "ayah": 10,
      "text": "فَمَا لَهٗ مِنْ قُوَّةٍ وَّلَا نَاصِرٍ ۝١٠ؕ",
      "status": "verified",
      "reviewer_comments": "",
      "updated_at": "2026-03-12T02:03:02.169081+00:00",
      "summary": {
        "total_noon_sakin": 1,
        "total_tanween": 2,
        "total_izhar": 0,
        "total_idgham": 2,
        "total_iqlab": 0,
        "total_ikhfa": 1
      },
      "explanations": [
        {
          "position": 13,
          "ayah": 10,
          "word": "مِنْ",
          "letter_position": "the last letter (position 2 of 2)",
          "next_word": "قُوَّةٍ",
          "next_letter": "ق",
          "rule": "ikhfa",
          "highlighting": {
            "primary_letter": {
              "start": 13,
              "end": 14,
              "letter": "ن",
              "full_char": "نْ",
              "index_in_word": 1
            },
            "word": {
              "start": 11,
              "end": 14,
              "text": "مِنْ",
              "segments": [
                {
                  "index": 0,
                  "letter": "م",
                  "full_char": "مِ",
                  "raw_char": "مِ",
                  "text_start": 11,
                  "text_end": 12
                },
                {
                  "index": 1,
                  "letter": "ن",
                  "full_char": "نْ",
                  "raw_char": "نْ",
                  "text_start": 13,
                  "text_end": 14
                }
              ]
            },
            "letter_index_in_word": 1,
            "total_letters_in_word": 2,
            "next_letter": {
              "start": 16,
              "end": 17,
              "letter": "ق",
              "full_char": "قُ",
              "index_in_word": 0
            },
            "next_word": {
              "start": 357,
              "end": 363,
              "text": "قُوَّةٍ",
              "segments": [
                {
                  "index": 0,
                  "letter": "ق",
                  "full_char": "قُ",
                  "raw_char": "قُ",
                  "text_start": 357,
                  "text_end": 358
                },
                {
                  "index": 1,
                  "letter": "و",
                  "full_char": "وَّ",
                  "raw_char": "وَّ",
                  "text_start": 359,
                  "text_end": 361
                },
                {
                  "index": 2,
                  "letter": "ة",
                  "full_char": "ةٍ",
                  "raw_char": "ةٍ",
                  "text_start": 362,
                  "text_end": 363
                }
              ]
            }
          },
          "explanation": "In the word 'مِنْ', at the last letter (position 2 of 2), we find Noon Sakin. The next letter 'ق' (from the word 'قُوَّةٍ') is not from the throat letters, not from Yarmaloon, not Ba, and not Alif. Therefore, we apply Ikhfa (إخفاء), which means you must hide or conceal the Noon with a nasal sound (ghunnah). The sound is between clear pronunciation and complete merging - not fully pronounced, not fully merged.",
          "urdu_explanation": "لفظ 'مِنْ' میں، آخری حرف ، نون ساکن ہے۔ اگلا حرف 'ق' (لفظ 'قُوَّةٍ' سے) نہ حلقی حروف میں سے ہے، نہ یرملون، نہ با، اور نہ الف۔ یہاں اخفاء ہوگا۔ نون کو غنہ کے ساتھ چھپا کر بولیں۔",
          "is_cross_ayah": false
        },
        {
          "position": 21,
          "ayah": 10,
          "word": "قُوَّةٍ",
          "letter_position": "the last letter (position 3 of 3)",
          "next_word": "وَّلَا",
          "next_letter": "و",
          "rule": "idgham_with_ghunnah",
          "highlighting": {
            "primary_letter": {
              "start": 21,
              "end": 22,
              "letter": "ة",
              "full_char": "ةٍ",
              "index_in_word": 2
            },
            "word": {
              "start": 16,
              "end": 22,
              "text": "قُوَّةٍ",
              "segments": [
                {
                  "index": 0,
                  "letter": "ق",
                  "full_char": "قُ",
                  "raw_char": "قُ",
                  "text_start": 16,
                  "text_end": 17
                },
                {
                  "index": 1,
                  "letter": "و",
                  "full_char": "وَّ",
                  "raw_char": "وَّ",
                  "text_start": 18,
                  "text_end": 20
                },
                {
                  "index": 2,
                  "letter": "ة",
                  "full_char": "ةٍ",
                  "raw_char": "ةٍ",
                  "text_start": 21,
                  "text_end": 22
                }
              ]
            },
            "letter_index_in_word": 2,
            "total_letters_in_word": 3,
            "next_letter": {
              "start": 24,
              "end": 26,
              "letter": "و",
              "full_char": "وَّ",
              "index_in_word": 0
            },
            "next_word": {
              "start": 365,
              "end": 370,
              "text": "وَّلَا",
              "segments": [
                {
                  "index": 0,
                  "letter": "و",
                  "full_char": "وَّ",
                  "raw_char": "وَّ",
                  "text_start": 365,
                  "text_end": 367
                },
                {
                  "index": 1,
                  "letter": "ل",
                  "full_char": "لَ",
                  "raw_char": "لَ",
                  "text_start": 368,
                  "text_end": 369
                },
                {
                  "index": 2,
                  "letter": "ا",
                  "full_char": "ا",
                  "raw_char": "ا",
                  "text_start": 370,
                  "text_end": 370
                }
              ]
            }
          },
          "explanation": "In the word 'قُوَّةٍ', at the last letter (position 3 of 3), we find Noon Tanween. The next letter 'و' (from the word 'وَّلَا') belongs to the Yarmaloon letters (ي ر م ل و ن). This means we apply Idgham (إدغام), which is the rule of merging. Since the letter 'و' is one of (ي و م ن), you must perform idgham with a nasal sound (ghunnah), also called Idgham with Ghunnah (إدغام بغنة).",
          "urdu_explanation": "لفظ 'قُوَّةٍ' میں، آخری حرف ، نون تنوین ہے۔ اگلا حرف 'و' (لفظ 'وَّلَا' سے) یرملون (ي ر م ل و ن) میں سے ہے۔ یہاں ادغام ہوگا۔ چونکہ 'و' (ی و م ن) میں سے ہے، اس لیے یہاں ادغام بغنہ ہوگا۔یعنی نون کو غنہ کے ساتھ ادا کریں۔",
          "is_cross_ayah": false
        },
        {
          "position": 36,
          "ayah": 10,
          "word": "نَاصِرٍ",
          "letter_position": "the last letter (position 4 of 4)",
          "next_word": "وَالسَّمَآءِ",
          "next_letter": "و",
          "rule": "idgham_with_ghunnah",
          "highlighting": {
            "primary_letter": {
              "start": 36,
              "end": 37,
              "letter": "ر",
              "full_char": "رٍ",
              "index_in_word": 3
            },
            "word": {
              "start": 31,
              "end": 37,
              "text": "نَاصِرٍ",
              "segments": [
                {
                  "index": 0,
                  "letter": "ن",
                  "full_char": "نَ",
                  "raw_char": "نَ",
                  "text_start": 31,
                  "text_end": 32
                },
                {
                  "index": 1,
                  "letter": "ا",
                  "full_char": "ا",
                  "raw_char": "ا",
                  "text_start": 33,
                  "text_end": 33
                },
                {
                  "index": 2,
                  "letter": "ص",
                  "full_char": "صِ",
                  "raw_char": "صِ",
                  "text_start": 34,
                  "text_end": 35
                },
                {
                  "index": 3,
                  "letter": "ر",
                  "full_char": "رٍ",
                  "raw_char": "رٍ",
                  "text_start": 36,
                  "text_end": 37
                }
              ]
            },
            "letter_index_in_word": 3,
            "total_letters_in_word": 4,
            "next_letter": null,
            "next_word": null
          },
          "explanation": "In the word 'نَاصِرٍ', at the last letter (position 4 of 4), we find Noon Tanween. The next letter 'و' (from the word 'وَالسَّمَآءِ') belongs to the Yarmaloon letters (ي ر م ل و ن). This means we apply Idgham (إدغام), which is the rule of merging. Since the letter 'و' is one of (ي و م ن), you must perform idgham with a nasal sound (ghunnah), also called Idgham with Ghunnah (إدغام بغنة).",
          "urdu_explanation": "لفظ 'نَاصِرٍ' میں، آخری حرف ، نون تنوین ہے۔ اگلا حرف 'و' (لفظ 'وَالسَّمَآءِ' سے) یرملون (ي ر م ل و ن) میں سے ہے۔ یہاں ادغام ہوگا۔ چونکہ 'و' (ی و م ن) میں سے ہے، اس لیے یہاں ادغام بغنہ ہوگا۔یعنی نون کو غنہ کے ساتھ ادا کریں۔",
          "is_cross_ayah": true,
          "next_letter_ayah": 11,
          "next_letter_offset": 0
        }
      ],
      "noon_sakin_positions": [
        13
      ],
      "tanween_positions": [
        21,
        36
      ],
      "izhar_halqi": [],
      "idgham": [
        [
          21,
          "و",
          true
        ],
        [
          36,
          "و",
          true
        ]
      ],
      "iqlab": [],
      "ikhfa": [
        [
          13,
          "ق"
        ]
      ]
    },
    {
      "ayah": 11,
      "text": "وَالسَّمَآءِ ذَاتِ الرَّجْعِ ۝١١ۙ",
      "status": "verified",
      "reviewer_comments": "",
      "updated_at": "2026-03-12T02:03:05.074180+00:00",
      "summary": {
        "total_noon_sakin": 0,
        "total_tanween": 0,
        "total_izhar": 0,
        "total_idgham": 0,
        "total_iqlab": 0,
        "total_ikhfa": 0
      },
      "explanations": [],
      "noon_sakin_positions": [],
      "tanween_positions": [],
      "izhar_halqi": [],
      "idgham": [],
      "iqlab": [],
      "ikhfa": []
    },
    {
      "ayah": 12,
      "text": "وَالْاَرْضِ ذَاتِ الصَّدْعِ ۝١٢ۙ",
      "status": "verified",
      "reviewer_comments": "",
      "updated_at": "2026-03-12T02:03:09.693976+00:00",
      "summary": {
        "total_noon_sakin": 0,
        "total_tanween": 0,
        "total_izhar": 0,
        "total_idgham": 0,
        "total_iqlab": 0,
        "total_ikhfa": 0
      },
      "explanations": [],
      "noon_sakin_positions": [],
      "tanween_positions": [],
      "izhar_halqi": [],
      "idgham": [],
      "iqlab": [],
      "ikhfa": []
    },
    {
      "ayah": 13,
      "text": "اِنَّهٗ لَقَوْلٌ فَصْلٌ ۝١٣ۙ",
      "status": "verified",
      "reviewer_comments": "",
      "updated_at": "2026-03-12T02:03:42.773592+00:00",
      "summary": {
        "total_noon_sakin": 1,
        "total_tanween": 2,
        "total_izhar": 0,
        "total_idgham": 2,
        "total_iqlab": 0,
        "total_ikhfa": 1
      },
      "explanations": [
        {
          "position": 2,
          "ayah": 13,
          "word": "اِنَّهٗ",
          "letter_position": "the 2nd letter (position 2 of 3)",
          "next_word": "اِنَّهٗ",
          "next_letter": "ن",
          "rule": "idgham_with_ghunnah",
          "highlighting": {
            "primary_letter": {
              "start": 2,
              "end": 4,
              "letter": "ن",
              "full_char": "نَّ",
              "index_in_word": 1
            },
            "word": {
              "start": 0,
              "end": 6,
              "text": "اِنَّهٗ",
              "segments": [
                {
                  "index": 0,
                  "letter": "ا",
                  "full_char": "اِ",
                  "raw_char": "اِ",
                  "text_start": 0,
                  "text_end": 1
                },
                {
                  "index": 1,
                  "letter": "ن",
                  "full_char": "نَّ",
                  "raw_char": "نَّ",
                  "text_start": 2,
                  "text_end": 4
                },
                {
                  "index": 2,
                  "letter": "ه",
                  "full_char": "هٗ",
                  "raw_char": "هٗ",
                  "text_start": 5,
                  "text_end": 6
                }
              ]
            },
            "letter_index_in_word": 1,
            "total_letters_in_word": 3,
            "next_letter": {
              "start": 5,
              "end": 6,
              "letter": "ه",
              "full_char": "هٗ",
              "index_in_word": 2
            },
            "next_word": null
          },
          "explanation": "In the word 'اِنَّهٗ', at the 2nd letter (position 2 of 3), we find Noon Sakin. The next letter 'ن' (within the same word) belongs to the Yarmaloon letters (ي ر م ل و ن). This means we apply Idgham (إدغام), which is the rule of merging. Since the letter 'ن' is one of (ي و م ن), you must perform idgham with a nasal sound (ghunnah), also called Idgham with Ghunnah (إدغام بغنة).",
          "urdu_explanation": "لفظ 'اِنَّهٗ' میں، دوسرا حرف ، نون ساکن ہے۔ اگلا حرف 'ن' (اسی لفظ میں) یرملون (ي ر م ل و ن) میں سے ہے۔ یہاں ادغام ہوگا۔ چونکہ 'ن' (ی و م ن) میں سے ہے، اس لیے یہاں ادغام بغنہ ہوگا۔یعنی نون کو غنہ کے ساتھ ادا کریں۔",
          "is_cross_ayah": false
        },
        {
          "position": 14,
          "ayah": 13,
          "word": "لَقَوْلٌ",
          "letter_position": "the last letter (position 4 of 4)",
          "next_word": "فَصْلٌ",
          "next_letter": "ف",
          "rule": "ikhfa",
          "highlighting": {
            "primary_letter": {
              "start": 14,
              "end": 15,
              "letter": "ل",
              "full_char": "لٌ",
              "index_in_word": 3
            },
            "word": {
              "start": 8,
              "end": 15,
              "text": "لَقَوْلٌ",
              "segments": [
                {
                  "index": 0,
                  "letter": "ل",
                  "full_char": "لَ",
                  "raw_char": "لَ",
                  "text_start": 8,
                  "text_end": 9
                },
                {
                  "index": 1,
                  "letter": "ق",
                  "full_char": "قَ",
                  "raw_char": "قَ",
                  "text_start": 10,
                  "text_end": 11
                },
                {
                  "index": 2,
                  "letter": "و",
                  "full_char": "وْ",
                  "raw_char": "وْ",
                  "text_start": 12,
                  "text_end": 13
                },
                {
                  "index": 3,
                  "letter": "ل",
                  "full_char": "لٌ",
                  "raw_char": "لٌ",
                  "text_start": 14,
                  "text_end": 15
                }
              ]
            },
            "letter_index_in_word": 3,
            "total_letters_in_word": 4,
            "next_letter": {
              "start": 17,
              "end": 18,
              "letter": "ف",
              "full_char": "فَ",
              "index_in_word": 0
            },
            "next_word": {
              "start": 470,
              "end": 475,
              "text": "فَصْلٌ",
              "segments": [
                {
                  "index": 0,
                  "letter": "ف",
                  "full_char": "فَ",
                  "raw_char": "فَ",
                  "text_start": 470,
                  "text_end": 471
                },
                {
                  "index": 1,
                  "letter": "ص",
                  "full_char": "صْ",
                  "raw_char": "صْ",
                  "text_start": 472,
                  "text_end": 473
                },
                {
                  "index": 2,
                  "letter": "ل",
                  "full_char": "لٌ",
                  "raw_char": "لٌ",
                  "text_start": 474,
                  "text_end": 475
                }
              ]
            }
          },
          "explanation": "In the word 'لَقَوْلٌ', at the last letter (position 4 of 4), we find Noon Tanween. The next letter 'ف' (from the word 'فَصْلٌ') is not from the throat letters, not from Yarmaloon, not Ba, and not Alif. Therefore, we apply Ikhfa (إخفاء), which means you must hide or conceal the Noon with a nasal sound (ghunnah). The sound is between clear pronunciation and complete merging - not fully pronounced, not fully merged.",
          "urdu_explanation": "لفظ 'لَقَوْلٌ' میں، آخری حرف ، نون تنوین ہے۔ اگلا حرف 'ف' (لفظ 'فَصْلٌ' سے) نہ حلقی حروف میں سے ہے، نہ یرملون، نہ با، اور نہ الف۔ یہاں اخفاء ہوگا۔ نون کو غنہ کے ساتھ چھپا کر بولیں۔",
          "is_cross_ayah": false
        },
        {
          "position": 21,
          "ayah": 13,
          "word": "فَصْلٌ",
          "letter_position": "the last letter (position 3 of 3)",
          "next_word": "وَّمَا",
          "next_letter": "و",
          "rule": "idgham_with_ghunnah",
          "highlighting": {
            "primary_letter": {
              "start": 21,
              "end": 22,
              "letter": "ل",
              "full_char": "لٌ",
              "index_in_word": 2
            },
            "word": {
              "start": 17,
              "end": 22,
              "text": "فَصْلٌ",
              "segments": [
                {
                  "index": 0,
                  "letter": "ف",
                  "full_char": "فَ",
                  "raw_char": "فَ",
                  "text_start": 17,
                  "text_end": 18
                },
                {
                  "index": 1,
                  "letter": "ص",
                  "full_char": "صْ",
                  "raw_char": "صْ",
                  "text_start": 19,
                  "text_end": 20
                },
                {
                  "index": 2,
                  "letter": "ل",
                  "full_char": "لٌ",
                  "raw_char": "لٌ",
                  "text_start": 21,
                  "text_end": 22
                }
              ]
            },
            "letter_index_in_word": 2,
            "total_letters_in_word": 3,
            "next_letter": null,
            "next_word": null
          },
          "explanation": "In the word 'فَصْلٌ', at the last letter (position 3 of 3), we find Noon Tanween. The next letter 'و' (from the word 'وَّمَا') belongs to the Yarmaloon letters (ي ر م ل و ن). This means we apply Idgham (إدغام), which is the rule of merging. Since the letter 'و' is one of (ي و م ن), you must perform idgham with a nasal sound (ghunnah), also called Idgham with Ghunnah (إدغام بغنة).",
          "urdu_explanation": "لفظ 'فَصْلٌ' میں، آخری حرف ، نون تنوین ہے۔ اگلا حرف 'و' (لفظ 'وَّمَا' سے) یرملون (ي ر م ل و ن) میں سے ہے۔ یہاں ادغام ہوگا۔ چونکہ 'و' (ی و م ن) میں سے ہے، اس لیے یہاں ادغام بغنہ ہوگا۔یعنی نون کو غنہ کے ساتھ ادا کریں۔",
          "is_cross_ayah": true,
          "next_letter_ayah": 14,
          "next_letter_offset": 0
        }
      ],
      "noon_sakin_positions": [
        2
      ],
      "tanween_positions": [
        14,
        21
      ],
      "izhar_halqi": [],
      "idgham": [
        [
          2,
          "ن",
          true
        ],
        [
          21,
          "و",
          true
        ]
      ],
      "iqlab": [],
      "ikhfa": [
        [
          14,
          "ف"
        ]
      ]
    },
    {
      "ayah": 14,
      "text": "وَّمَا هُوَ بِالْهَزْلِ ۝١٤ؕ",
      "status": "verified",
      "reviewer_comments": "",
      "updated_at": "2026-03-12T02:03:27.394437+00:00",
      "summary": {
        "total_noon_sakin": 0,
        "total_tanween": 0,
        "total_izhar": 0,
        "total_idgham": 0,
        "total_iqlab": 0,
        "total_ikhfa": 0
      },
      "explanations": [],
      "noon_sakin_positions": [],
      "tanween_positions": [],
      "izhar_halqi": [],
      "idgham": [],
      "iqlab": [],
      "ikhfa": []
    },
    {
      "ayah": 15,
      "text": "اِنَّهُمْ يَكِيْدُوْنَ كَيْدًا ۝١٥ۙ",
      "status": "verified",
      "reviewer_comments": "",
      "updated_at": "2026-03-12T02:03:30.030267+00:00",
      "summary": {
        "total_noon_sakin": 1,
        "total_tanween": 1,
        "total_izhar": 0,
        "total_idgham": 2,
        "total_iqlab": 0,
        "total_ikhfa": 0
      },
      "explanations": [
        {
          "position": 2,
          "ayah": 15,
          "word": "اِنَّهُمْ",
          "letter_position": "the 2nd letter (position 2 of 4)",
          "next_word": "اِنَّهُمْ",
          "next_letter": "ن",
          "rule": "idgham_with_ghunnah",
          "highlighting": {
            "primary_letter": {
              "start": 2,
              "end": 4,
              "letter": "ن",
              "full_char": "نَّ",
              "index_in_word": 1
            },
            "word": {
              "start": 0,
              "end": 8,
              "text": "اِنَّهُمْ",
              "segments": [
                {
                  "index": 0,
                  "letter": "ا",
                  "full_char": "اِ",
                  "raw_char": "اِ",
                  "text_start": 0,
                  "text_end": 1
                },
                {
                  "index": 1,
                  "letter": "ن",
                  "full_char": "نَّ",
                  "raw_char": "نَّ",
                  "text_start": 2,
                  "text_end": 4
                },
                {
                  "index": 2,
                  "letter": "ه",
                  "full_char": "هُ",
                  "raw_char": "هُ",
                  "text_start": 5,
                  "text_end": 6
                },
                {
                  "index": 3,
                  "letter": "م",
                  "full_char": "مْ",
                  "raw_char": "مْ",
                  "text_start": 7,
                  "text_end": 8
                }
              ]
            },
            "letter_index_in_word": 1,
            "total_letters_in_word": 4,
            "next_letter": {
              "start": 5,
              "end": 6,
              "letter": "ه",
              "full_char": "هُ",
              "index_in_word": 2
            },
            "next_word": null
          },
          "explanation": "In the word 'اِنَّهُمْ', at the 2nd letter (position 2 of 4), we find Noon Sakin. The next letter 'ن' (within the same word) belongs to the Yarmaloon letters (ي ر م ل و ن). This means we apply Idgham (إدغام), which is the rule of merging. Since the letter 'ن' is one of (ي و م ن), you must perform idgham with a nasal sound (ghunnah), also called Idgham with Ghunnah (إدغام بغنة).",
          "urdu_explanation": "لفظ 'اِنَّهُمْ' میں، دوسرا حرف ، نون ساکن ہے۔ اگلا حرف 'ن' (اسی لفظ میں) یرملون (ي ر م ل و ن) میں سے ہے۔ یہاں ادغام ہوگا۔ چونکہ 'ن' (ی و م ن) میں سے ہے، اس لیے یہاں ادغام بغنہ ہوگا۔یعنی نون کو غنہ کے ساتھ ادا کریں۔",
          "is_cross_ayah": false
        },
        {
          "position": 27,
          "ayah": 15,
          "word": "كَيْدًا",
          "letter_position": "the 3rd letter (position 3 of 4)",
          "next_word": "وَّاَكِيْدُ",
          "next_letter": "و",
          "rule": "idgham_with_ghunnah",
          "highlighting": {
            "primary_letter": {
              "start": 27,
              "end": 28,
              "letter": "د",
              "full_char": "دً",
              "index_in_word": 2
            },
            "word": {
              "start": 23,
              "end": 29,
              "text": "كَيْدًا",
              "segments": [
                {
                  "index": 0,
                  "letter": "ك",
                  "full_char": "كَ",
                  "raw_char": "كَ",
                  "text_start": 23,
                  "text_end": 24
                },
                {
                  "index": 1,
                  "letter": "ي",
                  "full_char": "يْ",
                  "raw_char": "يْ",
                  "text_start": 25,
                  "text_end": 26
                },
                {
                  "index": 2,
                  "letter": "د",
                  "full_char": "دً",
                  "raw_char": "دً",
                  "text_start": 27,
                  "text_end": 28
                },
                {
                  "index": 3,
                  "letter": "ا",
                  "full_char": "ا",
                  "raw_char": "ا",
                  "text_start": 29,
                  "text_end": 29
                }
              ]
            },
            "letter_index_in_word": 2,
            "total_letters_in_word": 4,
            "next_letter": null,
            "next_word": null
          },
          "explanation": "In the word 'كَيْدًا', at the 3rd letter (position 3 of 4), we find Noon Tanween. The next letter 'و' (from the word 'وَّاَكِيْدُ') belongs to the Yarmaloon letters (ي ر م ل و ن). This means we apply Idgham (إدغام), which is the rule of merging. Since the letter 'و' is one of (ي و م ن), you must perform idgham with a nasal sound (ghunnah), also called Idgham with Ghunnah (إدغام بغنة).",
          "urdu_explanation": "لفظ 'كَيْدًا' میں، تیسرا حرف ، نون تنوین ہے۔ اگلا حرف 'و' (لفظ 'وَّاَكِيْدُ' سے) یرملون (ي ر م ل و ن) میں سے ہے۔ یہاں ادغام ہوگا۔ چونکہ 'و' (ی و م ن) میں سے ہے، اس لیے یہاں ادغام بغنہ ہوگا۔یعنی نون کو غنہ کے ساتھ ادا کریں۔",
          "is_cross_ayah": true,
          "next_letter_ayah": 16,
          "next_letter_offset": 0
        }
      ],
      "noon_sakin_positions": [
        2
      ],
      "tanween_positions": [
        27
      ],
      "izhar_halqi": [],
      "idgham": [
        [
          2,
          "ن",
          true
        ],
        [
          27,
          "و",
          true
        ]
      ],
      "iqlab": [],
      "ikhfa": []
    },
    {
      "ayah": 16,
      "text": "وَّاَكِيْدُ كَيْدًا ۝١٦ۚۖ",
      "status": "verified",
      "reviewer_comments": "",
      "updated_at": "2026-03-12T02:03:32.386582+00:00",
      "summary": {
        "total_noon_sakin": 0,
        "total_tanween": 1,
        "total_izhar": 0,
        "total_idgham": 0,
        "total_iqlab": 0,
        "total_ikhfa": 1
      },
      "explanations": [
        {
          "position": 16,
          "ayah": 16,
          "word": "كَيْدًا",
          "letter_position": "the 3rd letter (position 3 of 4)",
          "next_word": "فَمَهِّلِ",
          "next_letter": "ف",
          "rule": "ikhfa",
          "highlighting": {
            "primary_letter": {
              "start": 16,
              "end": 17,
              "letter": "د",
              "full_char": "دً",
              "index_in_word": 2
            },
            "word": {
              "start": 12,
              "end": 18,
              "text": "كَيْدًا",
              "segments": [
                {
                  "index": 0,
                  "letter": "ك",
                  "full_char": "كَ",
                  "raw_char": "كَ",
                  "text_start": 12,
                  "text_end": 13
                },
                {
                  "index": 1,
                  "letter": "ي",
                  "full_char": "يْ",
                  "raw_char": "يْ",
                  "text_start": 14,
                  "text_end": 15
                },
                {
                  "index": 2,
                  "letter": "د",
                  "full_char": "دً",
                  "raw_char": "دً",
                  "text_start": 16,
                  "text_end": 17
                },
                {
                  "index": 3,
                  "letter": "ا",
                  "full_char": "ا",
                  "raw_char": "ا",
                  "text_start": 18,
                  "text_end": 18
                }
              ]
            },
            "letter_index_in_word": 2,
            "total_letters_in_word": 4,
            "next_letter": null,
            "next_word": null
          },
          "explanation": "In the word 'كَيْدًا', at the 3rd letter (position 3 of 4), we find Noon Tanween. The next letter 'ف' (from the word 'فَمَهِّلِ') is not from the throat letters, not from Yarmaloon, not Ba, and not Alif. Therefore, we apply Ikhfa (إخفاء), which means you must hide or conceal the Noon with a nasal sound (ghunnah). The sound is between clear pronunciation and complete merging - not fully pronounced, not fully merged.",
          "urdu_explanation": "لفظ 'كَيْدًا' میں، تیسرا حرف ، نون تنوین ہے۔ اگلا حرف 'ف' (لفظ 'فَمَهِّلِ' سے) نہ حلقی حروف میں سے ہے، نہ یرملون، نہ با، اور نہ الف۔ یہاں اخفاء ہوگا۔ نون کو غنہ کے ساتھ چھپا کر بولیں۔",
          "is_cross_ayah": true,
          "next_letter_ayah": 17,
          "next_letter_offset": 0
        }
      ],
      "noon_sakin_positions": [],
      "tanween_positions": [
        16
      ],
      "izhar_halqi": [],
      "idgham": [],
      "iqlab": [],
      "ikhfa": [
        [
          16,
          "ف"
        ]
      ]
    },
    {
      "ayah": 17,
      "text": "فَمَهِّلِ الْكٰفِرِيْنَ اَمْهِلْهُمْ رُوَيْدًا ۝١٧",
      "status": "verified",
      "reviewer_comments": "",
      "updated_at": "2026-03-12T02:03:34.622625+00:00",
      "summary": {
        "total_noon_sakin": 0,
        "total_tanween": 1,
        "total_izhar": 0,
        "total_idgham": 0,
        "total_iqlab": 0,
        "total_ikhfa": 0
      },
      "explanations": [],
      "noon_sakin_positions": [],
      "tanween_positions": [
        43
      ],
      "izhar_halqi": [],
      "idgham": [],
      "iqlab": [],
      "ikhfa": []
    }
  ]
}