{
  "metadata": {
    "surah": 51,
    "analysis_type": "qalqala",
    "schema_version": "1.0",
    "status": "pending",
    "updated_at": "2026-02-21T16:43:47.642393+00:00",
    "created_at": "2026-02-04T16:50:32.700334+00:00"
  },
  "data": {
    "text": "وَالذّٰرِيٰتِ ذَرْوًا ۝١ۙ فَالْحٰمِلٰتِ وِقْرًا ۝٢ۙ فَالْجٰرِيٰتِ يُسْرًا ۝٣ۙ فَالْمُقَسِّمٰتِ اَمْرًا ۝٤ۙ اِنَّمَا تُوْعَدُوْنَ لَصَادِقٌ ۝٥ۙ وَّاِنَّ الدِّيْنَ لَوَاقِعٌ ۝٦ؕ وَالسَّمَآءِ ذَاتِ الْحُبُكِ ۝٧ۙ اِنَّكُمْ لَفِيْ قَوْلٍ مُّخْتَلِفٍ ۝٨ۙ يُّو͏ٔ͏ْفَكُ عَنْهُ مَنْ اُفِكَ ۝٩ؕ قُتِلَ الْخَرّٰصُوْنَ ۝١٠ۙ الَّذِيْنَ هُمْ فِيْ غَمْرَةٍ سَاهُوْنَ ۝١١ۙ يَسْـَٔلُوْنَ اَيَّانَ يَوْمُ الدِّيْنِ ۝١٢ؕ يَوْمَ هُمْ عَلَي النَّارِ يُفْتَنُوْنَ ۝١٣ ذُوْقُوْا فِتْنَتَكُمْؕ هٰذَا الَّذِيْ كُنْتُمْ بِهٖ تَسْتَعْجِلُوْنَ ۝١٤ اِنَّ الْمُتَّقِيْنَ فِيْ جَنّٰتٍ وَّعُيُوْنٍ ۝١٥ۙ اٰخِذِيْنَ مَا͏ٓ اٰتٰىهُمْ رَبُّهُمْؕ اِنَّهُمْ كَانُوْا قَبْلَ ذٰلِكَ مُحْسِنِيْنَ ۝١٦ؕ كَانُوْا قَلِيْلًا مِّنَ الَّيْلِ مَا يَهْجَعُوْنَ ۝١٧ وَبِالْاَسْحَارِ هُمْ يَسْتَغْفِرُوْنَ ۝١٨ وَفِيْٓ اَمْوَالِهِمْ حَقٌّ لِّلسَّآىِٕلِ وَالْمَحْرُوْمِ ۝١٩ وَفِي الْاَرْضِ اٰيٰتٌ لِّلْمُوْقِنِيْنَ ۝٢٠ۙ وَفِيْٓ اَنْفُسِكُمْؕ اَفَلَا تُبْصِرُوْنَ ۝٢١ وَفِي السَّمَآءِ رِزْقُكُمْ وَمَا تُوْعَدُوْنَ ۝٢٢ فَوَرَبِّ السَّمَآءِ وَالْاَرْضِ اِنَّهٗ لَحَقٌّ مِّثْلَ مَا͏ٓ اَنَّكُمْ تَنْطِقُوْنَ ۝٢٣ هَلْ اَتٰىكَ حَدِيْثُ ضَيْفِ اِبْرٰهِيْمَ الْمُكْرَمِيْنَ ۝٢٤ۘ اِذْ دَخَلُوْا عَلَيْهِ فَقَالُوْا سَلٰمًاؕ قَالَ سَلٰمٌۚ قَوْمٌ مُّنْكَرُوْنَ ۝٢٥ فَرَاغَ اِلٰٓي اَهْلِهٖ فَجَآءَ بِعِجْلٍ سَمِيْنٍ ۝٢٦ۙ فَقَرَّبَهٗٓ اِلَيْهِمْ قَالَ اَلَا تَاْكُلُوْنَ ۝٢٧ؗ فَاَوْجَسَ مِنْهُمْ خِيْفَةًؕ قَالُوْا لَا تَخَفْؕ وَبَشَّرُوْهُ بِغُلٰمٍ عَلِيْمٍ ۝٢٨ فَاَقْبَلَتِ امْرَاَتُهٗ فِيْ صَرَّةٍ فَصَكَّتْ وَجْهَهَا وَقَالَتْ عَجُوْزٌ عَقِيْمٌ ۝٢٩ قَالُوْا كَذٰلِكِۙ قَالَ رَبُّكِؕ اِنَّهٗ هُوَ الْحَكِيْمُ الْعَلِيْمُ ۝٣٠ قَالَ فَمَا خَطْبُكُمْ اَيُّهَا الْمُرْسَلُوْنَ ۝٣١ قَالُوْٓا اِنَّا͏ٓ اُرْسِلْنَا͏ٓ اِلٰي قَوْمٍ مُّجْرِمِيْنَ ۝٣٢ۙ لِنُرْسِلَ عَلَيْهِمْ حِجَارَةً مِّنْ طِيْنٍ ۝٣٣ۙ مُّسَوَّمَةً عِنْدَ رَبِّكَ لِلْمُسْرِفِيْنَ ۝٣٤ فَاَخْرَجْنَا مَنْ كَانَ فِيْهَا مِنَ الْمُو͏ٔ͏ْمِنِيْنَ ۝٣٥ۚ فَمَا وَجَدْنَا فِيْهَا غَيْرَ بَيْتٍ مِّنَ الْمُسْلِمِيْنَ ۝٣٦ۚ وَتَرَكْنَا فِيْهَا͏ٓ اٰيَةً لِّلَّذِيْنَ يَخَافُوْنَ الْعَذَابَ الْاَلِيْمَ ۝٣٧ؕ وَفِيْ مُوْسٰٓي اِذْ اَرْسَلْنٰهُ اِلٰي فِرْعَوْنَ بِسُلْطٰنٍ مُّبِيْنٍ ۝٣٨ فَتَوَلّٰي بِرُكْنِهٖ وَقَالَ سٰحِرٌ اَوْ مَجْنُوْنٌ ۝٣٩ فَاَخَذْنٰهُ وَجُنُوْدَهٗ فَنَبَذْنٰهُمْ فِي الْيَمِّ وَهُوَ مُلِيْمٌ ۝٤٠ؕ وَفِيْ عَادٍ اِذْ اَرْسَلْنَا عَلَيْهِمُ الرِّيْحَ الْعَقِيْمَ ۝٤١ۚ مَا تَذَرُ مِنْ شَيْءٍ اَتَتْ عَلَيْهِ اِلَّا جَعَلَتْهُ كَالرَّمِيْمِ ۝٤٢ؕ وَفِيْ ثَمُوْدَ اِذْ قِيْلَ لَهُمْ تَمَتَّعُوْا حَتّٰي حِيْنٍ ۝٤٣ فَعَتَوْا عَنْ اَمْرِ رَبِّهِمْ فَاَخَذَتْهُمُ الصّٰعِقَةُ وَهُمْ يَنْظُرُوْنَ ۝٤٤ فَمَا اسْتَطَاعُوْا مِنْ قِيَامٍ وَّمَا كَانُوْا مُنْتَصِرِيْنَ ۝٤٥ۙ وَقَوْمَ نُوْحٍ مِّنْ قَبْلُؕ اِنَّهُمْ كَانُوْا قَوْمًا فٰسِقِيْنَ ۝٤٦ وَالسَّمَآءَ بَنَيْنٰهَا بِاَيْىدٍ وَّاِنَّا لَمُوْسِعُوْنَ ۝٤٧ وَالْاَرْضَ فَرَشْنٰهَا فَنِعْمَ الْمٰهِدُوْنَ ۝٤٨ وَمِنْ كُلِّ شَيْءٍ خَلَقْنَا زَوْجَيْنِ لَعَلَّكُمْ تَذَكَّرُوْنَ ۝٤٩ فَفِرُّوْٓا اِلَي اللّٰهِؕ اِنِّيْ لَكُمْ مِّنْهُ نَذِيْرٌ مُّبِيْنٌ ۝٥٠ۚ وَلَا تَجْعَلُوْا مَعَ اللّٰهِ اِلٰهًا اٰخَرَؕ اِنِّيْ لَكُمْ مِّنْهُ نَذِيْرٌ مُّبِيْنٌ ۝٥١ كَذٰلِكَ مَا͏ٓ اَتَي الَّذِيْنَ مِنْ قَبْلِهِمْ مِّنْ رَّسُوْلٍ اِلَّا قَالُوْا سَاحِرٌ اَوْ مَجْنُوْنٌ ۝٥٢ۚ اَتَوَاصَوْا بِهٖۚ بَلْ هُمْ قَوْمٌ طَاغُوْنَ ۝٥٣ۚ فَتَوَلَّ عَنْهُمْ فَمَا͏ٓ اَنْتَ بِمَلُوْمٍ ۝٥٤ؗ وَّذَكِّرْ فَاِنَّ الذِّكْرٰي تَنْفَعُ الْمُو͏ٔ͏ْمِنِيْنَ ۝٥٥ وَمَا خَلَقْتُ الْجِنَّ وَالْاِنْسَ اِلَّا لِيَعْبُدُوْنِ ۝٥٦ مَا͏ٓ اُرِيْدُ مِنْهُمْ مِّنْ رِّزْقٍ وَّمَا͏ٓ اُرِيْدُ اَنْ يُّطْعِمُوْنِ ۝٥٧ اِنَّ اللّٰهَ هُوَ الرَّزَّاقُ ذُو الْقُوَّةِ الْمَتِيْنُ ۝٥٨ فَاِنَّ لِلَّذِيْنَ ظَلَمُوْا ذَنُوْبًا مِّثْلَ ذَنُوْبِ اَصْحٰبِهِمْ فَلَا يَسْتَعْجِلُوْنِ ۝٥٩ فَوَيْلٌ لِّلَّذِيْنَ كَفَرُوْا مِنْ يَّوْمِهِمُ الَّذِيْ يُوْعَدُوْنَ ۝٦٠",
    "execution_mode": "optimized",
    "summary": {
      "total_qalqala": 19,
      "qalqala_sughra": 19,
      "qalqala_kubra": 0
    },
    "qalqala_letters": [
      "ق",
      "ط",
      "ب",
      "ج",
      "د"
    ],
    "explanations": [
      {
        "position": 42,
        "ayah": 1,
        "letter": "ق",
        "word": "وِقْرًا",
        "letter_position": "the 2nd letter (position 2 of 4)",
        "type": "Qalqala Sughra (Minor)",
        "rule": "qalqala_sughra",
        "is_sughra": true,
        "is_kubra": false,
        "highlighting": {
          "primary_letter": {
            "start": 42,
            "end": 43,
            "letter": "ق",
            "full_char": "قْ",
            "index_in_word": 1
          },
          "word": {
            "start": 40,
            "end": 46,
            "text": "وِقْرًا",
            "segments": [
              {
                "index": 0,
                "letter": "و",
                "full_char": "وِ",
                "raw_char": "وِ",
                "text_start": 40,
                "text_end": 41
              },
              {
                "index": 1,
                "letter": "ق",
                "full_char": "قْ",
                "raw_char": "قْ",
                "text_start": 42,
                "text_end": 43
              },
              {
                "index": 2,
                "letter": "ر",
                "full_char": "رً",
                "raw_char": "رً",
                "text_start": 44,
                "text_end": 45
              },
              {
                "index": 3,
                "letter": "ا",
                "full_char": "ا",
                "raw_char": "ا",
                "text_start": 46,
                "text_end": 46
              }
            ]
          },
          "letter_index_in_word": 1,
          "total_letters_in_word": 4
        },
        "explanation": "In the word 'وِقْرًا', at the 2nd letter (position 2 of 4), the letter 'ق' is sakin in the middle of the word. This is Qalqala Sughra (القلقلة الصغرى), meaning a light/minor echoing or vibrating sound. Pronounce the letter with a slight bounce or echo without fully releasing the pressure.",
        "urdu_explanation": "لفظ 'وِقْرًا' میں، حرف 'ق' لفظ کے درمیان میں ساکن ہے۔ یہ قلقلہ صغریٰ ہے۔ اس حرف کو ہلکی اچھال کے ساتھ پڑھیں۔"
      },
      {
        "position": 631,
        "ayah": 1,
        "letter": "ب",
        "word": "قَبْلَ",
        "letter_position": "the 2nd letter (position 2 of 3)",
        "type": "Qalqala Sughra (Minor)",
        "rule": "qalqala_sughra",
        "is_sughra": true,
        "is_kubra": false,
        "highlighting": {
          "primary_letter": {
            "start": 631,
            "end": 632,
            "letter": "ب",
            "full_char": "بْ",
            "index_in_word": 1
          },
          "word": {
            "start": 629,
            "end": 634,
            "text": "قَبْلَ",
            "segments": [
              {
                "index": 0,
                "letter": "ق",
                "full_char": "قَ",
                "raw_char": "قَ",
                "text_start": 629,
                "text_end": 630
              },
              {
                "index": 1,
                "letter": "ب",
                "full_char": "بْ",
                "raw_char": "بْ",
                "text_start": 631,
                "text_end": 632
              },
              {
                "index": 2,
                "letter": "ل",
                "full_char": "لَ",
                "raw_char": "لَ",
                "text_start": 633,
                "text_end": 634
              }
            ]
          },
          "letter_index_in_word": 1,
          "total_letters_in_word": 3
        },
        "explanation": "In the word 'قَبْلَ', at the 2nd letter (position 2 of 3), the letter 'ب' is sakin in the middle of the word. This is Qalqala Sughra (القلقلة الصغرى), meaning a light/minor echoing or vibrating sound. Pronounce the letter with a slight bounce or echo without fully releasing the pressure.",
        "urdu_explanation": "لفظ 'قَبْلَ' میں، حرف 'ب' لفظ کے درمیان میں ساکن ہے۔ یہ قلقلہ صغریٰ ہے۔ اس حرف کو ہلکی اچھال کے ساتھ پڑھیں۔"
      },
      {
        "position": 900,
        "ayah": 1,
        "letter": "ب",
        "word": "تُبْصِرُوْنَ",
        "letter_position": "the 2nd letter (position 2 of 6)",
        "type": "Qalqala Sughra (Minor)",
        "rule": "qalqala_sughra",
        "is_sughra": true,
        "is_kubra": false,
        "highlighting": {
          "primary_letter": {
            "start": 900,
            "end": 901,
            "letter": "ب",
            "full_char": "بْ",
            "index_in_word": 1
          },
          "word": {
            "start": 898,
            "end": 909,
            "text": "تُبْصِرُوْنَ",
            "segments": [
              {
                "index": 0,
                "letter": "ت",
                "full_char": "تُ",
                "raw_char": "تُ",
                "text_start": 898,
                "text_end": 899
              },
              {
                "index": 1,
                "letter": "ب",
                "full_char": "بْ",
                "raw_char": "بْ",
                "text_start": 900,
                "text_end": 901
              },
              {
                "index": 2,
                "letter": "ص",
                "full_char": "صِ",
                "raw_char": "صِ",
                "text_start": 902,
                "text_end": 903
              },
              {
                "index": 3,
                "letter": "ر",
                "full_char": "رُ",
                "raw_char": "رُ",
                "text_start": 904,
                "text_end": 905
              },
              {
                "index": 4,
                "letter": "و",
                "full_char": "وْ",
                "raw_char": "وْ",
                "text_start": 906,
                "text_end": 907
              },
              {
                "index": 5,
                "letter": "ن",
                "full_char": "نَ",
                "raw_char": "نَ",
                "text_start": 908,
                "text_end": 909
              }
            ]
          },
          "letter_index_in_word": 1,
          "total_letters_in_word": 6
        },
        "explanation": "In the word 'تُبْصِرُوْنَ', at the 2nd letter (position 2 of 6), the letter 'ب' is sakin in the middle of the word. This is Qalqala Sughra (القلقلة الصغرى), meaning a light/minor echoing or vibrating sound. Pronounce the letter with a slight bounce or echo without fully releasing the pressure.",
        "urdu_explanation": "لفظ 'تُبْصِرُوْنَ' میں، حرف 'ب' لفظ کے درمیان میں ساکن ہے۔ یہ قلقلہ صغریٰ ہے۔ اس حرف کو ہلکی اچھال کے ساتھ پڑھیں۔"
      },
      {
        "position": 1089,
        "ayah": 1,
        "letter": "ب",
        "word": "اِبْرٰهِيْمَ",
        "letter_position": "the 2nd letter (position 2 of 6)",
        "type": "Qalqala Sughra (Minor)",
        "rule": "qalqala_sughra",
        "is_sughra": true,
        "is_kubra": false,
        "highlighting": {
          "primary_letter": {
            "start": 1089,
            "end": 1090,
            "letter": "ب",
            "full_char": "بْ",
            "index_in_word": 1
          },
          "word": {
            "start": 1087,
            "end": 1098,
            "text": "اِبْرٰهِيْمَ",
            "segments": [
              {
                "index": 0,
                "letter": "ا",
                "full_char": "اِ",
                "raw_char": "اِ",
                "text_start": 1087,
                "text_end": 1088
              },
              {
                "index": 1,
                "letter": "ب",
                "full_char": "بْ",
                "raw_char": "بْ",
                "text_start": 1089,
                "text_end": 1090
              },
              {
                "index": 2,
                "letter": "ر",
                "full_char": "رٰ",
                "raw_char": "رٰ",
                "text_start": 1091,
                "text_end": 1092
              },
              {
                "index": 3,
                "letter": "ه",
                "full_char": "هِ",
                "raw_char": "هِ",
                "text_start": 1093,
                "text_end": 1094
              },
              {
                "index": 4,
                "letter": "ي",
                "full_char": "يْ",
                "raw_char": "يْ",
                "text_start": 1095,
                "text_end": 1096
              },
              {
                "index": 5,
                "letter": "م",
                "full_char": "مَ",
                "raw_char": "مَ",
                "text_start": 1097,
                "text_end": 1098
              }
            ]
          },
          "letter_index_in_word": 1,
          "total_letters_in_word": 6
        },
        "explanation": "In the word 'اِبْرٰهِيْمَ', at the 2nd letter (position 2 of 6), the letter 'ب' is sakin in the middle of the word. This is Qalqala Sughra (القلقلة الصغرى), meaning a light/minor echoing or vibrating sound. Pronounce the letter with a slight bounce or echo without fully releasing the pressure.",
        "urdu_explanation": "لفظ 'اِبْرٰهِيْمَ' میں، حرف 'ب' لفظ کے درمیان میں ساکن ہے۔ یہ قلقلہ صغریٰ ہے۔ اس حرف کو ہلکی اچھال کے ساتھ پڑھیں۔"
      },
      {
        "position": 1241,
        "ayah": 1,
        "letter": "ج",
        "word": "بِعِجْلٍ",
        "letter_position": "the 3rd letter (position 3 of 4)",
        "type": "Qalqala Sughra (Minor)",
        "rule": "qalqala_sughra",
        "is_sughra": true,
        "is_kubra": false,
        "highlighting": {
          "primary_letter": {
            "start": 1241,
            "end": 1242,
            "letter": "ج",
            "full_char": "جْ",
            "index_in_word": 2
          },
          "word": {
            "start": 1237,
            "end": 1244,
            "text": "بِعِجْلٍ",
            "segments": [
              {
                "index": 0,
                "letter": "ب",
                "full_char": "بِ",
                "raw_char": "بِ",
                "text_start": 1237,
                "text_end": 1238
              },
              {
                "index": 1,
                "letter": "ع",
                "full_char": "عِ",
                "raw_char": "عِ",
                "text_start": 1239,
                "text_end": 1240
              },
              {
                "index": 2,
                "letter": "ج",
                "full_char": "جْ",
                "raw_char": "جْ",
                "text_start": 1241,
                "text_end": 1242
              },
              {
                "index": 3,
                "letter": "ل",
                "full_char": "لٍ",
                "raw_char": "لٍ",
                "text_start": 1243,
                "text_end": 1244
              }
            ]
          },
          "letter_index_in_word": 2,
          "total_letters_in_word": 4
        },
        "explanation": "In the word 'بِعِجْلٍ', at the 3rd letter (position 3 of 4), the letter 'ج' is sakin in the middle of the word. This is Qalqala Sughra (القلقلة الصغرى), meaning a light/minor echoing or vibrating sound. Pronounce the letter with a slight bounce or echo without fully releasing the pressure.",
        "urdu_explanation": "لفظ 'بِعِجْلٍ' میں، حرف 'ج' لفظ کے درمیان میں ساکن ہے۔ یہ قلقلہ صغریٰ ہے۔ اس حرف کو ہلکی اچھال کے ساتھ پڑھیں۔"
      },
      {
        "position": 1405,
        "ayah": 1,
        "letter": "ق",
        "word": "فَاَقْبَلَتِ",
        "letter_position": "the 3rd letter (position 3 of 6)",
        "type": "Qalqala Sughra (Minor)",
        "rule": "qalqala_sughra",
        "is_sughra": true,
        "is_kubra": false,
        "highlighting": {
          "primary_letter": {
            "start": 1405,
            "end": 1406,
            "letter": "ق",
            "full_char": "قْ",
            "index_in_word": 2
          },
          "word": {
            "start": 1401,
            "end": 1412,
            "text": "فَاَقْبَلَتِ",
            "segments": [
              {
                "index": 0,
                "letter": "ف",
                "full_char": "فَ",
                "raw_char": "فَ",
                "text_start": 1401,
                "text_end": 1402
              },
              {
                "index": 1,
                "letter": "ا",
                "full_char": "اَ",
                "raw_char": "اَ",
                "text_start": 1403,
                "text_end": 1404
              },
              {
                "index": 2,
                "letter": "ق",
                "full_char": "قْ",
                "raw_char": "قْ",
                "text_start": 1405,
                "text_end": 1406
              },
              {
                "index": 3,
                "letter": "ب",
                "full_char": "بَ",
                "raw_char": "بَ",
                "text_start": 1407,
                "text_end": 1408
              },
              {
                "index": 4,
                "letter": "ل",
                "full_char": "لَ",
                "raw_char": "لَ",
                "text_start": 1409,
                "text_end": 1410
              },
              {
                "index": 5,
                "letter": "ت",
                "full_char": "تِ",
                "raw_char": "تِ",
                "text_start": 1411,
                "text_end": 1412
              }
            ]
          },
          "letter_index_in_word": 2,
          "total_letters_in_word": 6
        },
        "explanation": "In the word 'فَاَقْبَلَتِ', at the 3rd letter (position 3 of 6), the letter 'ق' is sakin in the middle of the word. This is Qalqala Sughra (القلقلة الصغرى), meaning a light/minor echoing or vibrating sound. Pronounce the letter with a slight bounce or echo without fully releasing the pressure.",
        "urdu_explanation": "لفظ 'فَاَقْبَلَتِ' میں، حرف 'ق' لفظ کے درمیان میں ساکن ہے۔ یہ قلقلہ صغریٰ ہے۔ اس حرف کو ہلکی اچھال کے ساتھ پڑھیں۔"
      },
      {
        "position": 1451,
        "ayah": 1,
        "letter": "ج",
        "word": "وَجْهَهَا",
        "letter_position": "the 2nd letter (position 2 of 5)",
        "type": "Qalqala Sughra (Minor)",
        "rule": "qalqala_sughra",
        "is_sughra": true,
        "is_kubra": false,
        "highlighting": {
          "primary_letter": {
            "start": 1451,
            "end": 1452,
            "letter": "ج",
            "full_char": "جْ",
            "index_in_word": 1
          },
          "word": {
            "start": 1449,
            "end": 1457,
            "text": "وَجْهَهَا",
            "segments": [
              {
                "index": 0,
                "letter": "و",
                "full_char": "وَ",
                "raw_char": "وَ",
                "text_start": 1449,
                "text_end": 1450
              },
              {
                "index": 1,
                "letter": "ج",
                "full_char": "جْ",
                "raw_char": "جْ",
                "text_start": 1451,
                "text_end": 1452
              },
              {
                "index": 2,
                "letter": "ه",
                "full_char": "هَ",
                "raw_char": "هَ",
                "text_start": 1453,
                "text_end": 1454
              },
              {
                "index": 3,
                "letter": "ه",
                "full_char": "هَ",
                "raw_char": "هَ",
                "text_start": 1455,
                "text_end": 1456
              },
              {
                "index": 4,
                "letter": "ا",
                "full_char": "ا",
                "raw_char": "ا",
                "text_start": 1457,
                "text_end": 1457
              }
            ]
          },
          "letter_index_in_word": 1,
          "total_letters_in_word": 5
        },
        "explanation": "In the word 'وَجْهَهَا', at the 2nd letter (position 2 of 5), the letter 'ج' is sakin in the middle of the word. This is Qalqala Sughra (القلقلة الصغرى), meaning a light/minor echoing or vibrating sound. Pronounce the letter with a slight bounce or echo without fully releasing the pressure.",
        "urdu_explanation": "لفظ 'وَجْهَهَا' میں، حرف 'ج' لفظ کے درمیان میں ساکن ہے۔ یہ قلقلہ صغریٰ ہے۔ اس حرف کو ہلکی اچھال کے ساتھ پڑھیں۔"
      },
      {
        "position": 1580,
        "ayah": 1,
        "letter": "ط",
        "word": "خَطْبُكُمْ",
        "letter_position": "the 2nd letter (position 2 of 5)",
        "type": "Qalqala Sughra (Minor)",
        "rule": "qalqala_sughra",
        "is_sughra": true,
        "is_kubra": false,
        "highlighting": {
          "primary_letter": {
            "start": 1580,
            "end": 1581,
            "letter": "ط",
            "full_char": "طْ",
            "index_in_word": 1
          },
          "word": {
            "start": 1578,
            "end": 1587,
            "text": "خَطْبُكُمْ",
            "segments": [
              {
                "index": 0,
                "letter": "خ",
                "full_char": "خَ",
                "raw_char": "خَ",
                "text_start": 1578,
                "text_end": 1579
              },
              {
                "index": 1,
                "letter": "ط",
                "full_char": "طْ",
                "raw_char": "طْ",
                "text_start": 1580,
                "text_end": 1581
              },
              {
                "index": 2,
                "letter": "ب",
                "full_char": "بُ",
                "raw_char": "بُ",
                "text_start": 1582,
                "text_end": 1583
              },
              {
                "index": 3,
                "letter": "ك",
                "full_char": "كُ",
                "raw_char": "كُ",
                "text_start": 1584,
                "text_end": 1585
              },
              {
                "index": 4,
                "letter": "م",
                "full_char": "مْ",
                "raw_char": "مْ",
                "text_start": 1586,
                "text_end": 1587
              }
            ]
          },
          "letter_index_in_word": 1,
          "total_letters_in_word": 5
        },
        "explanation": "In the word 'خَطْبُكُمْ', at the 2nd letter (position 2 of 5), the letter 'ط' is sakin in the middle of the word. This is Qalqala Sughra (القلقلة الصغرى), meaning a light/minor echoing or vibrating sound. Pronounce the letter with a slight bounce or echo without fully releasing the pressure.",
        "urdu_explanation": "لفظ 'خَطْبُكُمْ' میں، حرف 'ط' لفظ کے درمیان میں ساکن ہے۔ یہ قلقلہ صغریٰ ہے۔ اس حرف کو ہلکی اچھال کے ساتھ پڑھیں۔"
      },
      {
        "position": 1667,
        "ayah": 1,
        "letter": "ج",
        "word": "مُّجْرِمِيْنَ",
        "letter_position": "the 2nd letter (position 2 of 6)",
        "type": "Qalqala Sughra (Minor)",
        "rule": "qalqala_sughra",
        "is_sughra": true,
        "is_kubra": false,
        "highlighting": {
          "primary_letter": {
            "start": 1667,
            "end": 1668,
            "letter": "ج",
            "full_char": "جْ",
            "index_in_word": 1
          },
          "word": {
            "start": 1664,
            "end": 1676,
            "text": "مُّجْرِمِيْنَ",
            "segments": [
              {
                "index": 0,
                "letter": "م",
                "full_char": "مُّ",
                "raw_char": "مُّ",
                "text_start": 1664,
                "text_end": 1666
              },
              {
                "index": 1,
                "letter": "ج",
                "full_char": "جْ",
                "raw_char": "جْ",
                "text_start": 1667,
                "text_end": 1668
              },
              {
                "index": 2,
                "letter": "ر",
                "full_char": "رِ",
                "raw_char": "رِ",
                "text_start": 1669,
                "text_end": 1670
              },
              {
                "index": 3,
                "letter": "م",
                "full_char": "مِ",
                "raw_char": "مِ",
                "text_start": 1671,
                "text_end": 1672
              },
              {
                "index": 4,
                "letter": "ي",
                "full_char": "يْ",
                "raw_char": "يْ",
                "text_start": 1673,
                "text_end": 1674
              },
              {
                "index": 5,
                "letter": "ن",
                "full_char": "نَ",
                "raw_char": "نَ",
                "text_start": 1675,
                "text_end": 1676
              }
            ]
          },
          "letter_index_in_word": 1,
          "total_letters_in_word": 6
        },
        "explanation": "In the word 'مُّجْرِمِيْنَ', at the 2nd letter (position 2 of 6), the letter 'ج' is sakin in the middle of the word. This is Qalqala Sughra (القلقلة الصغرى), meaning a light/minor echoing or vibrating sound. Pronounce the letter with a slight bounce or echo without fully releasing the pressure.",
        "urdu_explanation": "لفظ 'مُّجْرِمِيْنَ' میں، حرف 'ج' لفظ کے درمیان میں ساکن ہے۔ یہ قلقلہ صغریٰ ہے۔ اس حرف کو ہلکی اچھال کے ساتھ پڑھیں۔"
      },
      {
        "position": 1790,
        "ayah": 1,
        "letter": "ج",
        "word": "فَاَخْرَجْنَا",
        "letter_position": "the 5th letter (position 5 of 7)",
        "type": "Qalqala Sughra (Minor)",
        "rule": "qalqala_sughra",
        "is_sughra": true,
        "is_kubra": false,
        "highlighting": {
          "primary_letter": {
            "start": 1790,
            "end": 1791,
            "letter": "ج",
            "full_char": "جْ",
            "index_in_word": 4
          },
          "word": {
            "start": 1782,
            "end": 1794,
            "text": "فَاَخْرَجْنَا",
            "segments": [
              {
                "index": 0,
                "letter": "ف",
                "full_char": "فَ",
                "raw_char": "فَ",
                "text_start": 1782,
                "text_end": 1783
              },
              {
                "index": 1,
                "letter": "ا",
                "full_char": "اَ",
                "raw_char": "اَ",
                "text_start": 1784,
                "text_end": 1785
              },
              {
                "index": 2,
                "letter": "خ",
                "full_char": "خْ",
                "raw_char": "خْ",
                "text_start": 1786,
                "text_end": 1787
              },
              {
                "index": 3,
                "letter": "ر",
                "full_char": "رَ",
                "raw_char": "رَ",
                "text_start": 1788,
                "text_end": 1789
              },
              {
                "index": 4,
                "letter": "ج",
                "full_char": "جْ",
                "raw_char": "جْ",
                "text_start": 1790,
                "text_end": 1791
              },
              {
                "index": 5,
                "letter": "ن",
                "full_char": "نَ",
                "raw_char": "نَ",
                "text_start": 1792,
                "text_end": 1793
              },
              {
                "index": 6,
                "letter": "ا",
                "full_char": "ا",
                "raw_char": "ا",
                "text_start": 1794,
                "text_end": 1794
              }
            ]
          },
          "letter_index_in_word": 4,
          "total_letters_in_word": 7
        },
        "explanation": "In the word 'فَاَخْرَجْنَا', at the 5th letter (position 5 of 7), the letter 'ج' is sakin in the middle of the word. This is Qalqala Sughra (القلقلة الصغرى), meaning a light/minor echoing or vibrating sound. Pronounce the letter with a slight bounce or echo without fully releasing the pressure.",
        "urdu_explanation": "لفظ 'فَاَخْرَجْنَا' میں، حرف 'ج' لفظ کے درمیان میں ساکن ہے۔ یہ قلقلہ صغریٰ ہے۔ اس حرف کو ہلکی اچھال کے ساتھ پڑھیں۔"
      },
      {
        "position": 1854,
        "ayah": 1,
        "letter": "د",
        "word": "وَجَدْنَا",
        "letter_position": "the 3rd letter (position 3 of 5)",
        "type": "Qalqala Sughra (Minor)",
        "rule": "qalqala_sughra",
        "is_sughra": true,
        "is_kubra": false,
        "highlighting": {
          "primary_letter": {
            "start": 1854,
            "end": 1855,
            "letter": "د",
            "full_char": "دْ",
            "index_in_word": 2
          },
          "word": {
            "start": 1850,
            "end": 1858,
            "text": "وَجَدْنَا",
            "segments": [
              {
                "index": 0,
                "letter": "و",
                "full_char": "وَ",
                "raw_char": "وَ",
                "text_start": 1850,
                "text_end": 1851
              },
              {
                "index": 1,
                "letter": "ج",
                "full_char": "جَ",
                "raw_char": "جَ",
                "text_start": 1852,
                "text_end": 1853
              },
              {
                "index": 2,
                "letter": "د",
                "full_char": "دْ",
                "raw_char": "دْ",
                "text_start": 1854,
                "text_end": 1855
              },
              {
                "index": 3,
                "letter": "ن",
                "full_char": "نَ",
                "raw_char": "نَ",
                "text_start": 1856,
                "text_end": 1857
              },
              {
                "index": 4,
                "letter": "ا",
                "full_char": "ا",
                "raw_char": "ا",
                "text_start": 1858,
                "text_end": 1858
              }
            ]
          },
          "letter_index_in_word": 2,
          "total_letters_in_word": 5
        },
        "explanation": "In the word 'وَجَدْنَا', at the 3rd letter (position 3 of 5), the letter 'د' is sakin in the middle of the word. This is Qalqala Sughra (القلقلة الصغرى), meaning a light/minor echoing or vibrating sound. Pronounce the letter with a slight bounce or echo without fully releasing the pressure.",
        "urdu_explanation": "لفظ 'وَجَدْنَا' میں، حرف 'د' لفظ کے درمیان میں ساکن ہے۔ یہ قلقلہ صغریٰ ہے۔ اس حرف کو ہلکی اچھال کے ساتھ پڑھیں۔"
      },
      {
        "position": 2111,
        "ayah": 1,
        "letter": "ج",
        "word": "مَجْنُوْنٌ",
        "letter_position": "the 2nd letter (position 2 of 5)",
        "type": "Qalqala Sughra (Minor)",
        "rule": "qalqala_sughra",
        "is_sughra": true,
        "is_kubra": false,
        "highlighting": {
          "primary_letter": {
            "start": 2111,
            "end": 2112,
            "letter": "ج",
            "full_char": "جْ",
            "index_in_word": 1
          },
          "word": {
            "start": 2109,
            "end": 2118,
            "text": "مَجْنُوْنٌ",
            "segments": [
              {
                "index": 0,
                "letter": "م",
                "full_char": "مَ",
                "raw_char": "مَ",
                "text_start": 2109,
                "text_end": 2110
              },
              {
                "index": 1,
                "letter": "ج",
                "full_char": "جْ",
                "raw_char": "جْ",
                "text_start": 2111,
                "text_end": 2112
              },
              {
                "index": 2,
                "letter": "ن",
                "full_char": "نُ",
                "raw_char": "نُ",
                "text_start": 2113,
                "text_end": 2114
              },
              {
                "index": 3,
                "letter": "و",
                "full_char": "وْ",
                "raw_char": "وْ",
                "text_start": 2115,
                "text_end": 2116
              },
              {
                "index": 4,
                "letter": "ن",
                "full_char": "نٌ",
                "raw_char": "نٌ",
                "text_start": 2117,
                "text_end": 2118
              }
            ]
          },
          "letter_index_in_word": 1,
          "total_letters_in_word": 5
        },
        "explanation": "In the word 'مَجْنُوْنٌ', at the 2nd letter (position 2 of 5), the letter 'ج' is sakin in the middle of the word. This is Qalqala Sughra (القلقلة الصغرى), meaning a light/minor echoing or vibrating sound. Pronounce the letter with a slight bounce or echo without fully releasing the pressure.",
        "urdu_explanation": "لفظ 'مَجْنُوْنٌ' میں، حرف 'ج' لفظ کے درمیان میں ساکن ہے۔ یہ قلقلہ صغریٰ ہے۔ اس حرف کو ہلکی اچھال کے ساتھ پڑھیں۔"
      },
      {
        "position": 2585,
        "ayah": 1,
        "letter": "ب",
        "word": "قَبْلُؕ",
        "letter_position": "the 2nd letter (position 2 of 3)",
        "type": "Qalqala Sughra (Minor)",
        "rule": "qalqala_sughra",
        "is_sughra": true,
        "is_kubra": false,
        "highlighting": {
          "primary_letter": {
            "start": 2585,
            "end": 2586,
            "letter": "ب",
            "full_char": "بْ",
            "index_in_word": 1
          },
          "word": {
            "start": 2583,
            "end": 2589,
            "text": "قَبْلُؕ",
            "segments": [
              {
                "index": 0,
                "letter": "ق",
                "full_char": "قَ",
                "raw_char": "قَ",
                "text_start": 2583,
                "text_end": 2584
              },
              {
                "index": 1,
                "letter": "ب",
                "full_char": "بْ",
                "raw_char": "بْ",
                "text_start": 2585,
                "text_end": 2586
              },
              {
                "index": 2,
                "letter": "ل",
                "full_char": "لُ",
                "raw_char": "لُؕ",
                "text_start": 2587,
                "text_end": 2589
              }
            ]
          },
          "letter_index_in_word": 1,
          "total_letters_in_word": 3
        },
        "explanation": "In the word 'قَبْلُؕ', at the 2nd letter (position 2 of 3), the letter 'ب' is sakin in the middle of the word. This is Qalqala Sughra (القلقلة الصغرى), meaning a light/minor echoing or vibrating sound. Pronounce the letter with a slight bounce or echo without fully releasing the pressure.",
        "urdu_explanation": "لفظ 'قَبْلُؕ' میں، حرف 'ب' لفظ کے درمیان میں ساکن ہے۔ یہ قلقلہ صغریٰ ہے۔ اس حرف کو ہلکی اچھال کے ساتھ پڑھیں۔"
      },
      {
        "position": 2773,
        "ayah": 1,
        "letter": "ق",
        "word": "خَلَقْنَا",
        "letter_position": "the 3rd letter (position 3 of 5)",
        "type": "Qalqala Sughra (Minor)",
        "rule": "qalqala_sughra",
        "is_sughra": true,
        "is_kubra": false,
        "highlighting": {
          "primary_letter": {
            "start": 2773,
            "end": 2774,
            "letter": "ق",
            "full_char": "قْ",
            "index_in_word": 2
          },
          "word": {
            "start": 2769,
            "end": 2777,
            "text": "خَلَقْنَا",
            "segments": [
              {
                "index": 0,
                "letter": "خ",
                "full_char": "خَ",
                "raw_char": "خَ",
                "text_start": 2769,
                "text_end": 2770
              },
              {
                "index": 1,
                "letter": "ل",
                "full_char": "لَ",
                "raw_char": "لَ",
                "text_start": 2771,
                "text_end": 2772
              },
              {
                "index": 2,
                "letter": "ق",
                "full_char": "قْ",
                "raw_char": "قْ",
                "text_start": 2773,
                "text_end": 2774
              },
              {
                "index": 3,
                "letter": "ن",
                "full_char": "نَ",
                "raw_char": "نَ",
                "text_start": 2775,
                "text_end": 2776
              },
              {
                "index": 4,
                "letter": "ا",
                "full_char": "ا",
                "raw_char": "ا",
                "text_start": 2777,
                "text_end": 2777
              }
            ]
          },
          "letter_index_in_word": 2,
          "total_letters_in_word": 5
        },
        "explanation": "In the word 'خَلَقْنَا', at the 3rd letter (position 3 of 5), the letter 'ق' is sakin in the middle of the word. This is Qalqala Sughra (القلقلة الصغرى), meaning a light/minor echoing or vibrating sound. Pronounce the letter with a slight bounce or echo without fully releasing the pressure.",
        "urdu_explanation": "لفظ 'خَلَقْنَا' میں، حرف 'ق' لفظ کے درمیان میں ساکن ہے۔ یہ قلقلہ صغریٰ ہے۔ اس حرف کو ہلکی اچھال کے ساتھ پڑھیں۔"
      },
      {
        "position": 2902,
        "ayah": 1,
        "letter": "ج",
        "word": "تَجْعَلُوْا",
        "letter_position": "the 2nd letter (position 2 of 6)",
        "type": "Qalqala Sughra (Minor)",
        "rule": "qalqala_sughra",
        "is_sughra": true,
        "is_kubra": false,
        "highlighting": {
          "primary_letter": {
            "start": 2902,
            "end": 2903,
            "letter": "ج",
            "full_char": "جْ",
            "index_in_word": 1
          },
          "word": {
            "start": 2900,
            "end": 2910,
            "text": "تَجْعَلُوْا",
            "segments": [
              {
                "index": 0,
                "letter": "ت",
                "full_char": "تَ",
                "raw_char": "تَ",
                "text_start": 2900,
                "text_end": 2901
              },
              {
                "index": 1,
                "letter": "ج",
                "full_char": "جْ",
                "raw_char": "جْ",
                "text_start": 2902,
                "text_end": 2903
              },
              {
                "index": 2,
                "letter": "ع",
                "full_char": "عَ",
                "raw_char": "عَ",
                "text_start": 2904,
                "text_end": 2905
              },
              {
                "index": 3,
                "letter": "ل",
                "full_char": "لُ",
                "raw_char": "لُ",
                "text_start": 2906,
                "text_end": 2907
              },
              {
                "index": 4,
                "letter": "و",
                "full_char": "وْ",
                "raw_char": "وْ",
                "text_start": 2908,
                "text_end": 2909
              },
              {
                "index": 5,
                "letter": "ا",
                "full_char": "ا",
                "raw_char": "ا",
                "text_start": 2910,
                "text_end": 2910
              }
            ]
          },
          "letter_index_in_word": 1,
          "total_letters_in_word": 6
        },
        "explanation": "In the word 'تَجْعَلُوْا', at the 2nd letter (position 2 of 6), the letter 'ج' is sakin in the middle of the word. This is Qalqala Sughra (القلقلة الصغرى), meaning a light/minor echoing or vibrating sound. Pronounce the letter with a slight bounce or echo without fully releasing the pressure.",
        "urdu_explanation": "لفظ 'تَجْعَلُوْا' میں، حرف 'ج' لفظ کے درمیان میں ساکن ہے۔ یہ قلقلہ صغریٰ ہے۔ اس حرف کو ہلکی اچھال کے ساتھ پڑھیں۔"
      },
      {
        "position": 3026,
        "ayah": 1,
        "letter": "ب",
        "word": "قَبْلِهِمْ",
        "letter_position": "the 2nd letter (position 2 of 5)",
        "type": "Qalqala Sughra (Minor)",
        "rule": "qalqala_sughra",
        "is_sughra": true,
        "is_kubra": false,
        "highlighting": {
          "primary_letter": {
            "start": 3026,
            "end": 3027,
            "letter": "ب",
            "full_char": "بْ",
            "index_in_word": 1
          },
          "word": {
            "start": 3024,
            "end": 3033,
            "text": "قَبْلِهِمْ",
            "segments": [
              {
                "index": 0,
                "letter": "ق",
                "full_char": "قَ",
                "raw_char": "قَ",
                "text_start": 3024,
                "text_end": 3025
              },
              {
                "index": 1,
                "letter": "ب",
                "full_char": "بْ",
                "raw_char": "بْ",
                "text_start": 3026,
                "text_end": 3027
              },
              {
                "index": 2,
                "letter": "ل",
                "full_char": "لِ",
                "raw_char": "لِ",
                "text_start": 3028,
                "text_end": 3029
              },
              {
                "index": 3,
                "letter": "ه",
                "full_char": "هِ",
                "raw_char": "هِ",
                "text_start": 3030,
                "text_end": 3031
              },
              {
                "index": 4,
                "letter": "م",
                "full_char": "مْ",
                "raw_char": "مْ",
                "text_start": 3032,
                "text_end": 3033
              }
            ]
          },
          "letter_index_in_word": 1,
          "total_letters_in_word": 5
        },
        "explanation": "In the word 'قَبْلِهِمْ', at the 2nd letter (position 2 of 5), the letter 'ب' is sakin in the middle of the word. This is Qalqala Sughra (القلقلة الصغرى), meaning a light/minor echoing or vibrating sound. Pronounce the letter with a slight bounce or echo without fully releasing the pressure.",
        "urdu_explanation": "لفظ 'قَبْلِهِمْ' میں، حرف 'ب' لفظ کے درمیان میں ساکن ہے۔ یہ قلقلہ صغریٰ ہے۔ اس حرف کو ہلکی اچھال کے ساتھ پڑھیں۔"
      },
      {
        "position": 3082,
        "ayah": 1,
        "letter": "ج",
        "word": "مَجْنُوْنٌ",
        "letter_position": "the 2nd letter (position 2 of 5)",
        "type": "Qalqala Sughra (Minor)",
        "rule": "qalqala_sughra",
        "is_sughra": true,
        "is_kubra": false,
        "highlighting": {
          "primary_letter": {
            "start": 3082,
            "end": 3083,
            "letter": "ج",
            "full_char": "جْ",
            "index_in_word": 1
          },
          "word": {
            "start": 3080,
            "end": 3089,
            "text": "مَجْنُوْنٌ",
            "segments": [
              {
                "index": 0,
                "letter": "م",
                "full_char": "مَ",
                "raw_char": "مَ",
                "text_start": 3080,
                "text_end": 3081
              },
              {
                "index": 1,
                "letter": "ج",
                "full_char": "جْ",
                "raw_char": "جْ",
                "text_start": 3082,
                "text_end": 3083
              },
              {
                "index": 2,
                "letter": "ن",
                "full_char": "نُ",
                "raw_char": "نُ",
                "text_start": 3084,
                "text_end": 3085
              },
              {
                "index": 3,
                "letter": "و",
                "full_char": "وْ",
                "raw_char": "وْ",
                "text_start": 3086,
                "text_end": 3087
              },
              {
                "index": 4,
                "letter": "ن",
                "full_char": "نٌ",
                "raw_char": "نٌ",
                "text_start": 3088,
                "text_end": 3089
              }
            ]
          },
          "letter_index_in_word": 1,
          "total_letters_in_word": 5
        },
        "explanation": "In the word 'مَجْنُوْنٌ', at the 2nd letter (position 2 of 5), the letter 'ج' is sakin in the middle of the word. This is Qalqala Sughra (القلقلة الصغرى), meaning a light/minor echoing or vibrating sound. Pronounce the letter with a slight bounce or echo without fully releasing the pressure.",
        "urdu_explanation": "لفظ 'مَجْنُوْنٌ' میں، حرف 'ج' لفظ کے درمیان میں ساکن ہے۔ یہ قلقلہ صغریٰ ہے۔ اس حرف کو ہلکی اچھال کے ساتھ پڑھیں۔"
      },
      {
        "position": 3269,
        "ayah": 1,
        "letter": "ق",
        "word": "خَلَقْتُ",
        "letter_position": "the 3rd letter (position 3 of 4)",
        "type": "Qalqala Sughra (Minor)",
        "rule": "qalqala_sughra",
        "is_sughra": true,
        "is_kubra": false,
        "highlighting": {
          "primary_letter": {
            "start": 3269,
            "end": 3270,
            "letter": "ق",
            "full_char": "قْ",
            "index_in_word": 2
          },
          "word": {
            "start": 3265,
            "end": 3272,
            "text": "خَلَقْتُ",
            "segments": [
              {
                "index": 0,
                "letter": "خ",
                "full_char": "خَ",
                "raw_char": "خَ",
                "text_start": 3265,
                "text_end": 3266
              },
              {
                "index": 1,
                "letter": "ل",
                "full_char": "لَ",
                "raw_char": "لَ",
                "text_start": 3267,
                "text_end": 3268
              },
              {
                "index": 2,
                "letter": "ق",
                "full_char": "قْ",
                "raw_char": "قْ",
                "text_start": 3269,
                "text_end": 3270
              },
              {
                "index": 3,
                "letter": "ت",
                "full_char": "تُ",
                "raw_char": "تُ",
                "text_start": 3271,
                "text_end": 3272
              }
            ]
          },
          "letter_index_in_word": 2,
          "total_letters_in_word": 4
        },
        "explanation": "In the word 'خَلَقْتُ', at the 3rd letter (position 3 of 4), the letter 'ق' is sakin in the middle of the word. This is Qalqala Sughra (القلقلة الصغرى), meaning a light/minor echoing or vibrating sound. Pronounce the letter with a slight bounce or echo without fully releasing the pressure.",
        "urdu_explanation": "لفظ 'خَلَقْتُ' میں، حرف 'ق' لفظ کے درمیان میں ساکن ہے۔ یہ قلقلہ صغریٰ ہے۔ اس حرف کو ہلکی اچھال کے ساتھ پڑھیں۔"
      },
      {
        "position": 3385,
        "ayah": 1,
        "letter": "ط",
        "word": "يُّطْعِمُوْنِ",
        "letter_position": "the 2nd letter (position 2 of 6)",
        "type": "Qalqala Sughra (Minor)",
        "rule": "qalqala_sughra",
        "is_sughra": true,
        "is_kubra": false,
        "highlighting": {
          "primary_letter": {
            "start": 3385,
            "end": 3386,
            "letter": "ط",
            "full_char": "طْ",
            "index_in_word": 1
          },
          "word": {
            "start": 3382,
            "end": 3394,
            "text": "يُّطْعِمُوْنِ",
            "segments": [
              {
                "index": 0,
                "letter": "ي",
                "full_char": "يُّ",
                "raw_char": "يُّ",
                "text_start": 3382,
                "text_end": 3384
              },
              {
                "index": 1,
                "letter": "ط",
                "full_char": "طْ",
                "raw_char": "طْ",
                "text_start": 3385,
                "text_end": 3386
              },
              {
                "index": 2,
                "letter": "ع",
                "full_char": "عِ",
                "raw_char": "عِ",
                "text_start": 3387,
                "text_end": 3388
              },
              {
                "index": 3,
                "letter": "م",
                "full_char": "مُ",
                "raw_char": "مُ",
                "text_start": 3389,
                "text_end": 3390
              },
              {
                "index": 4,
                "letter": "و",
                "full_char": "وْ",
                "raw_char": "وْ",
                "text_start": 3391,
                "text_end": 3392
              },
              {
                "index": 5,
                "letter": "ن",
                "full_char": "نِ",
                "raw_char": "نِ",
                "text_start": 3393,
                "text_end": 3394
              }
            ]
          },
          "letter_index_in_word": 1,
          "total_letters_in_word": 6
        },
        "explanation": "In the word 'يُّطْعِمُوْنِ', at the 2nd letter (position 2 of 6), the letter 'ط' is sakin in the middle of the word. This is Qalqala Sughra (القلقلة الصغرى), meaning a light/minor echoing or vibrating sound. Pronounce the letter with a slight bounce or echo without fully releasing the pressure.",
        "urdu_explanation": "لفظ 'يُّطْعِمُوْنِ' میں، حرف 'ط' لفظ کے درمیان میں ساکن ہے۔ یہ قلقلہ صغریٰ ہے۔ اس حرف کو ہلکی اچھال کے ساتھ پڑھیں۔"
      }
    ],
    "positions": [
      [
        42,
        "ق"
      ],
      [
        631,
        "ب"
      ],
      [
        900,
        "ب"
      ],
      [
        1089,
        "ب"
      ],
      [
        1241,
        "ج"
      ],
      [
        1405,
        "ق"
      ],
      [
        1451,
        "ج"
      ],
      [
        1580,
        "ط"
      ],
      [
        1667,
        "ج"
      ],
      [
        1790,
        "ج"
      ],
      [
        1854,
        "د"
      ],
      [
        2111,
        "ج"
      ],
      [
        2585,
        "ب"
      ],
      [
        2773,
        "ق"
      ],
      [
        2902,
        "ج"
      ],
      [
        3026,
        "ب"
      ],
      [
        3082,
        "ج"
      ],
      [
        3269,
        "ق"
      ],
      [
        3385,
        "ط"
      ]
    ]
  }
}